<?xml version="1.0"?>
<opencv_storage>
<PatternName>enter11</PatternName>
<Descriptors type_id="opencv-matrix">
  <rows>500</rows>
  <cols>32</cols>
  <dt>u</dt>
  <data>
    104 32 56 96 5 77 83 16 97 0 172 8 159 27 0 48 144 212 76 8 8 32 208
    2 227 253 0 16 98 138 66 34 230 34 132 135 172 10 140 136 11 178 130
    249 195 40 213 142 65 197 236 149 60 70 207 130 140 18 207 191 132
    126 18 4 6 164 136 139 220 163 139 200 22 49 89 18 80 234 120 72 89
    10 19 177 18 50 91 151 76 6 139 108 156 75 176 128 34 177 32 8 221
    213 144 207 3 109 188 45 42 156 94 20 157 155 215 17 158 42 242 149
    43 84 20 255 211 12 214 223 0 140 15 190 28 195 7 232 22 3 66 2 112
    241 40 96 89 106 50 43 35 176 27 63 105 38 143 4 16 40 52 162 80 34
    30 176 42 194 49 72 172 4 198 163 223 215 34 80 166 53 237 128 0 193
    131 64 209 225 43 131 32 0 37 99 0 48 57 96 32 77 81 16 96 8 36 8 23
    23 0 48 128 20 92 8 1 96 176 0 195 169 33 0 64 0 70 34 41 36 113 65
    85 79 99 80 113 96 100 8 19 17 20 52 88 204 18 40 169 178 240 14 101
    156 0 32 75 136 82 160 103 109 104 66 205 85 198 232 193 208 173 10
    80 248 127 35 216 200 83 235 196 35 190 176 51 8 197 61 85 123 242
    198 2 4 143 177 130 38 189 55 60 51 74 211 149 39 40 75 55 87 51 165
    48 220 17 66 77 166 254 132 164 80 161 112 131 15 131 140 148 162 42
    67 20 128 90 199 40 226 33 196 120 107 2 212 55 152 4 238 32 36 138
    128 156 77 57 156 32 201 9 138 212 133 134 229 6 1 72 66 176 144 32
    64 200 42 19 208 83 42 88 61 45 4 142 104 88 10 176 170 34 172 42
    152 93 199 139 194 150 4 72 11 48 220 54 0 217 42 19 5 34 186 18 191
    121 6 155 41 85 8 116 202 34 172 42 152 93 197 138 198 150 69 72 131
    32 204 54 0 217 42 147 5 6 170 18 191 121 7 158 105 81 12 180 202 80
    56 27 178 2 204 17 64 172 136 32 8 182 215 32 80 160 49 89 0 1 65
    146 96 209 161 42 10 0 0 39 51 41 36 121 97 116 15 107 16 113 0 108
    8 19 19 16 48 90 204 6 40 169 178 240 14 103 141 32 0 99 138 66 160
    38 160 129 155 221 163 138 200 22 49 81 26 192 200 121 136 89 74 51
    177 50 114 91 178 13 22 159 108 149 75 176 130 3 32 71 73 68 27 160
    64 92 96 82 70 200 136 148 164 122 12 122 13 133 240 101 192 6 26
    139 128 79 140 89 132 40 36 120 97 84 15 107 16 113 32 108 8 19 3 16
    48 90 140 2 40 169 178 240 14 103 141 32 32 97 138 66 160 24 12 15
    191 20 66 111 34 52 2 194 2 215 35 32 65 114 229 61 170 104 216 1 46
    229 167 250 0 36 248 49 40 247 34 132 135 173 26 140 136 27 178 131
    251 195 40 213 142 1 196 232 151 44 65 205 130 152 114 207 183 132
    126 26 4 38 168 1 154 221 197 131 200 150 17 232 10 176 216 120 0
    217 170 19 145 19 35 90 179 61 20 143 126 209 10 240 130 39 105 232
    66 205 85 198 200 195 208 168 10 80 216 127 43 216 200 19 227 198 99
    190 176 51 8 205 61 85 123 242 198 3 27 2 175 18 130 42 112 52 64 90
    231 117 227 176 64 118 111 19 205 129 152 5 108 36 36 170 128 44 162
    33 145 163 248 19 138 93 133 194 224 143 8 129 72 166 216 33 128 216
    168 26 66 75 35 90 189 177 144 139 58 24 11 48 138 82 2 14 169 10 2
    104 0 52 36 194 135 197 3 18 64 118 141 253 133 12 209 69 0 192 227
    171 145 36 132 57 64 32 161 1 139 212 133 140 239 6 1 104 74 176 136
    56 0 216 10 2 145 82 42 80 149 45 20 142 104 17 10 240 136 104 48 56
    96 32 12 81 16 97 8 52 8 159 23 0 48 132 20 93 8 128 96 176 0 195
    249 32 0 66 128 66 35 91 34 4 169 9 15 72 88 39 36 194 133 207 3 18
    64 204 141 253 133 12 193 209 144 208 241 139 16 58 4 56 18 97 56 8
    56 45 157 80 88 207 248 176 77 134 216 86 16 201 165 78 5 142 99 218
    17 147 217 1 58 88 12 90 6 72 48 25 240 1 109 17 19 44 9 32 24 190
    23 64 16 128 21 93 0 1 108 144 0 193 169 50 0 64 0 7 58 104 48 56 96
    32 77 81 16 105 136 52 8 159 23 0 48 132 21 221 8 136 96 176 0 195
    249 32 16 64 128 66 35 104 32 121 96 4 77 81 16 96 8 164 8 19 17 0
    48 136 148 68 8 8 96 240 0 195 201 32 17 96 128 70 34 80 34 30 161
    34 10 57 80 44 36 214 163 205 135 2 80 38 149 237 129 0 209 129 64
    208 225 43 129 36 128 37 67 72 56 56 112 32 205 81 22 233 136 52 8
    159 151 0 48 132 55 221 8 136 104 176 32 195 249 48 16 64 128 66 43
    104 49 56 96 48 77 83 16 105 128 108 8 159 23 0 48 148 28 93 72 8 48
    176 0 227 253 32 16 64 130 66 34 82 34 74 136 74 64 56 72 166 4 208
    163 13 198 34 80 110 157 239 129 8 67 138 208 144 225 171 139 21 4
    39 195 96 56 57 112 32 204 81 22 233 8 52 8 151 151 0 48 132 54 93 8
    136 104 176 32 195 249 48 16 64 128 66 43 104 32 121 96 36 77 81 16
    96 12 52 40 23 17 128 48 128 148 68 8 8 96 224 0 195 201 32 17 96
    128 70 35 51 32 78 137 77 27 160 72 78 32 194 2 193 136 54 160 104
    140 122 133 132 243 199 208 20 105 139 49 93 12 121 132 70 4 135 151
    140 38 172 141 180 155 211 82 64 234 57 203 121 103 59 179 49 209 11
    192 60 34 223 196 140 121 177 0 35 48 16 73 77 29 224 72 207 96 240
    76 138 216 22 180 200 12 82 12 133 115 214 208 23 24 1 58 91 12 90
    148 33 48 119 65 103 91 224 64 95 96 114 106 72 152 148 164 122 12
    210 8 133 242 245 208 22 24 3 34 95 12 91 164 124 60 208 190 180 170
    86 188 27 128 248 40 239 123 9 81 215 255 149 114 42 74 200 173 186
    255 36 186 182 251 82 11 2 34 6 137 74 3 168 72 46 36 210 231 192
    134 32 64 110 157 111 132 0 211 195 208 148 32 139 128 21 4 37 144
    35 32 5 137 76 11 160 72 94 96 82 70 208 8 148 96 120 12 122 5 133
    240 85 208 4 56 139 32 93 8 89 132 104 96 120 96 4 77 81 16 96 0 36
    8 23 17 0 48 136 132 64 72 8 96 240 0 195 201 0 16 96 130 70 34 80
    48 81 64 34 72 1 16 32 8 50 104 23 23 128 112 34 20 108 0 1 64 160 0
    145 160 32 128 32 128 6 35 104 32 17 64 77 89 81 0 105 32 36 8 10 21
    4 180 128 20 194 8 1 96 224 192 7 216 1 50 66 12 70 36 74 186 26 248
    35 204 49 151 189 13 94 33 191 151 32 80 134 59 189 0 2 24 146 227
    195 245 58 139 2 4 135 123 39 181 123 74 246 181 250 217 123 73 125
    98 24 216 252 180 255 155 6 152 151 50 190 247 63 29 35 238 213 131
    235 165 96 32 49 64 32 73 65 16 96 44 48 40 18 21 128 48 0 20 68 8 1
    96 224 0 65 168 33 48 64 0 70 35 72 48 17 64 1 72 1 0 97 32 38 8 30
    23 0 180 0 20 232 0 1 64 176 0 131 249 1 34 66 0 6 32 252 4 207 228
    69 102 107 88 49 130 231 18 83 67 57 123 120 236 17 234 41 215 184
    10 211 235 193 4 35 251 114 32 80 56 26 242 3 204 17 64 173 8 160 8
    190 223 32 80 166 51 93 0 2 75 146 97 209 241 2 11 0 0 39 19 90 34
    87 168 74 64 57 88 165 4 210 163 77 199 160 84 102 149 239 128 0 195
    131 192 208 32 170 137 39 132 37 113 0 145 27 170 20 197 129 117 6 9
    64 64 180 145 32 64 216 42 19 1 83 170 82 29 233 164 186 72 16 10
    176 170 16 137 11 172 20 199 129 101 4 9 64 2 177 147 32 64 200 42
    19 136 83 168 16 29 225 164 170 64 16 8 176 170 80 56 26 242 3 204
    17 64 173 0 160 8 62 223 32 80 166 179 93 0 2 75 146 97 211 241 10
    11 0 0 39 19 33 32 113 65 100 27 232 80 125 96 112 74 136 8 148 164
    122 140 22 8 133 242 229 192 6 24 130 32 79 140 82 164 121 97 98 76
    93 95 71 104 65 32 236 10 19 217 54 180 88 168 82 106 72 35 252 157
    115 221 129 57 115 190 118 230 16 157 11 174 20 199 35 254 22 8 74
    66 115 243 40 64 217 106 2 168 11 152 25 63 225 166 162 0 16 10 48
    42 16 141 11 173 20 199 165 103 4 1 74 2 49 179 32 64 104 42 19 136
    120 152 17 31 225 165 154 64 48 8 180 42 0 140 11 158 20 197 131 230
    150 9 72 2 176 250 48 64 217 42 19 129 34 170 18 63 105 38 154 72 16
    8 176 138 0 140 11 154 93 197 131 230 150 17 72 16 176 216 48 64 201
    42 19 129 34 42 18 55 105 22 158 104 16 8 176 138 32 233 9 170 124
    133 135 245 6 9 88 64 176 144 48 64 200 42 19 217 83 42 74 61 41 132
    174 104 24 10 176 168 152 76 10 188 21 198 65 101 20 4 198 18 51 19
    32 65 104 160 25 232 104 157 17 191 227 227 146 17 50 8 52 10 43 172
    97 73 85 27 234 218 87 97 124 206 160 72 158 164 89 138 18 173 167
    186 117 159 46 30 129 36 127 140 88 212 72 48 81 161 34 8 57 16 45 8
    50 232 159 23 128 212 38 21 221 8 1 64 129 192 196 240 42 130 6 128
    7 49 80 2 78 161 10 2 121 16 52 4 214 167 205 135 2 80 118 149 239
    133 8 209 133 64 212 163 170 129 36 128 37 83 97 34 40 40 12 157 192
    72 206 124 176 77 131 200 86 0 200 160 110 5 142 99 222 17 210 89
    169 60 93 12 90 196 64 48 57 96 0 76 81 16 96 200 36 8 22 23 0 48 0
    20 68 8 1 96 176 0 193 169 32 0 64 0 70 50 40 97 120 96 5 77 81 16
    96 0 36 8 23 17 0 48 136 144 64 72 8 96 240 0 195 201 0 16 96 130 70
    34 167 198 225 83 197 53 207 190 81 71 61 214 64 108 159 173 89 194
    146 175 253 102 125 162 46 30 213 132 223 223 216 220 36 173 3 154
    221 197 131 200 150 17 232 10 240 208 104 0 217 10 2 208 19 43 90
    179 57 20 143 124 144 10 176 162 64 48 25 224 0 76 81 16 40 8 32 8
    150 23 0 80 132 21 93 8 1 64 144 0 193 169 32 0 64 0 7 51 40 48 56
    96 33 77 81 16 97 8 52 8 31 23 0 48 132 17 85 8 136 96 48 0 195 217
    32 16 66 128 66 35 16 12 135 189 4 194 111 98 180 2 66 2 113 35 48
    65 96 230 59 139 105 217 17 44 229 162 218 0 36 240 49 40 90 56 81
    224 34 24 120 16 45 8 178 232 143 31 128 180 166 149 221 0 1 64 128
    192 146 249 43 130 106 128 11 49 104 32 56 96 37 77 83 16 97 0 172 8
    159 27 0 16 144 148 76 8 8 32 240 2 227 221 0 17 98 138 66 34 154
    205 6 188 21 130 76 39 165 0 194 2 43 2 32 65 96 163 25 192 104 137
    0 237 177 225 206 1 48 16 177 10 120 32 112 64 109 89 80 64 105 40
    180 40 10 25 148 52 202 148 196 8 8 98 224 192 87 217 0 51 99 136 70
    39 96 48 57 96 1 77 81 16 97 0 36 8 22 23 0 48 128 20 80 8 1 96 176
    0 195 185 0 16 66 128 70 50 1 32 69 65 69 91 160 64 126 96 226 66
    200 8 148 228 122 12 122 9 133 240 117 208 4 58 3 0 95 12 89 164 91
    2 4 165 40 10 72 16 45 96 210 197 207 2 18 66 102 197 253 133 140
    209 69 204 196 243 170 144 46 132 57 20 33 32 117 65 69 79 225 82
    117 96 100 72 18 17 148 180 88 140 82 8 129 242 245 192 5 24 128 0
    75 136 82 164 89 2 8 165 48 14 90 48 52 36 198 205 215 35 18 80 118
    197 125 141 140 208 209 6 214 231 170 128 40 128 9 80 64 56 57 96 32
    140 89 18 40 8 48 8 151 31 0 80 132 181 76 8 136 104 144 32 195 249
    48 16 64 128 67 43 81 205 111 229 22 6 239 55 100 64 206 194 241 39
    144 97 118 198 29 237 201 152 53 13 225 169 174 128 37 176 241 104
    88 2 94 160 42 66 25 16 52 36 214 163 223 7 2 80 54 149 237 128 8
    209 129 64 208 227 43 129 36 128 37 67 35 32 33 73 109 29 192 88 79
    104 176 76 138 24 148 164 200 4 90 13 133 98 255 208 7 24 1 58 91 12
    90 132 91 2 12 165 8 6 120 16 52 100 198 197 205 11 18 64 118 197
    253 133 140 209 213 12 196 227 234 145 44 132 57 80 146 30 63 191 50
    194 63 114 188 206 218 231 245 239 34 65 246 119 189 161 32 201 11
    111 240 167 234 131 36 32 37 83 148 72 15 190 4 194 75 96 148 2 195
    2 115 67 41 65 122 225 31 234 104 133 25 61 209 163 234 0 52 187 49
    34 18 32 66 137 76 137 232 65 173 0 242 2 142 10 16 64 106 129 78
    129 8 179 65 192 148 16 138 144 69 8 99 128 35 32 32 73 109 29 192
    88 79 104 176 76 138 24 148 164 200 4 90 13 141 98 255 208 7 24 1 58
    91 12 90 132 150 222 174 178 138 96 191 166 156 87 147 183 69 110
    191 75 103 83 189 135 244 197 46 226 232 35 254 131 141 117 181 87
    67 56 6 152 73 132 170 66 172 64 194 197 172 194 54 196 228 171 123
    133 7 139 150 227 144 52 154 10 8 4 43 156 120 32 112 64 109 89 80
    64 121 40 180 40 11 25 148 52 218 128 86 8 8 98 224 194 87 221 0 51
    99 136 70 39 64 48 57 224 32 12 89 16 41 8 48 8 151 31 0 80 134 149
    93 0 136 96 144 0 195 249 32 128 64 128 3 35 152 196 30 177 34 75
    188 167 188 51 2 178 223 62 40 67 167 85 253 33 96 221 1 213 229 227
    127 21 20 88 129 11 90 2 110 161 42 2 25 16 52 4 214 167 207 7 2 80
    118 149 237 129 8 193 193 64 208 227 170 129 36 128 37 83 134 94 238
    158 42 48 186 136 154 214 145 183 72 238 255 75 119 81 187 199 164
    69 46 226 2 34 223 135 157 117 61 87 244 76 12 191 44 6 79 184 132
    186 150 0 243 99 17 75 64 228 125 235 104 69 203 40 193 227 227 144
    48 249 16 32 214 20 159 181 162 34 57 19 60 19 19 243 221 47 9 75 39
    23 125 161 48 213 1 64 196 163 250 132 164 224 161 17 2 0 66 129 76
    137 232 65 45 32 242 2 140 10 48 80 106 136 78 129 0 51 193 192 148
    32 130 176 21 8 113 128 18 32 66 137 76 136 232 65 45 0 178 2 140 10
    16 0 106 129 78 129 8 163 65 192 148 16 138 128 69 8 99 128 18 32 66
    137 76 136 232 65 45 0 176 2 142 10 16 16 106 129 78 129 8 35 65 192
    148 16 138 152 69 8 99 128 167 70 229 19 236 51 142 157 87 127 21
    215 72 108 159 175 93 194 179 175 245 102 111 162 38 26 221 132 223
    255 248 212 92 20 159 165 172 110 84 27 168 187 131 48 215 59 73 75
    227 85 125 51 57 197 211 0 211 227 123 21 160 105 21 3 40 168 156
    185 205 229 144 207 158 17 32 25 164 154 98 10 201 11 234 17 22 106
    210 177 77 147 30 123 144 72 155 138 64 32 121 96 32 72 65 16 96 136
    52 40 23 23 0 48 2 20 76 8 1 96 160 0 193 169 33 0 96 128 70 35 49
    48 119 73 79 91 176 72 111 96 240 42 72 152 180 164 234 156 242 1
    133 243 231 208 22 72 3 43 95 12 107 135 17 0 71 65 13 91 160 64 126
    96 226 2 203 24 148 228 122 12 122 9 5 240 117 208 149 122 3 16 111
    12 89 164 189 197 236 99 157 63 78 188 81 114 189 30 83 125 31 51
    217 198 21 111 252 102 125 170 107 223 197 52 247 255 210 118 74 2
    70 169 66 6 121 16 55 44 214 167 77 135 130 84 126 141 47 140 136
    210 197 208 84 34 170 128 39 132 36 113 151 20 236 147 142 50 158
    136 150 247 145 183 193 108 255 11 95 71 123 183 189 69 255 224 78 2
    223 149 157 125 181 84 74 2 12 169 72 6 105 16 53 36 198 141 209 3
    18 80 84 140 123 140 136 210 209 64 213 163 139 0 42 132 96 112 245
    237 108 118 141 125 214 232 193 210 165 24 82 121 95 59 217 194 89
    111 236 103 250 186 123 219 197 63 83 127 210 70 35 56 17 73 77 29
    192 78 203 240 160 76 138 152 84 180 200 0 82 12 135 106 247 209 7
    24 17 62 91 12 90 156 49 48 122 72 79 93 176 72 238 96 240 14 78 216
    54 160 170 12 250 5 133 243 150 208 22 89 3 59 79 12 91 135 90 2 46
    161 74 2 121 16 52 4 198 167 77 7 2 80 118 157 175 133 136 210 193
    64 215 227 171 129 32 128 44 112 33 48 58 89 109 157 224 72 206 104
    48 76 146 216 54 160 168 36 90 13 133 113 250 144 23 89 3 50 89 12
    91 132 2 180 189 177 170 104 185 7 170 247 2 179 149 63 64 11 167 23
    123 145 50 92 147 64 205 2 95 231 132 64 133 242 66 34 71 201 74 2
    41 88 39 4 214 231 73 135 160 84 110 157 239 140 0 211 163 208 84 32
    170 136 39 132 37 241 104 56 56 96 33 13 81 18 105 8 52 8 159 19 0
    48 132 20 93 8 136 104 144 0 195 217 32 16 66 128 74 35 96 32 57 96
    36 73 81 16 96 12 180 40 19 19 128 48 136 148 76 8 8 34 224 0 195
    169 32 17 64 136 70 35 88 56 58 114 1 205 80 86 169 8 36 8 190 159
    32 144 160 55 221 0 0 105 146 224 211 249 16 11 74 0 15 27 83 48 83
    241 34 152 56 0 173 128 178 232 143 150 196 244 166 181 254 128 5 65
    144 192 150 248 11 146 42 128 11 21 104 48 56 96 32 12 81 16 105 136
    60 8 159 23 0 48 132 20 93 8 136 32 176 0 195 249 32 16 72 130 74 35
    64 48 17 224 0 77 81 16 44 136 32 72 150 23 0 48 128 21 76 8 1 96
    176 0 193 160 34 0 72 0 7 51 105 36 121 96 84 79 99 16 113 0 108 8
    19 19 16 48 24 204 2 8 9 178 240 10 103 189 0 0 96 138 66 162 112 97
    57 96 4 77 67 0 96 4 172 8 19 21 0 48 8 148 64 72 9 34 240 0 195 137
    0 16 96 10 70 34 35 160 104 9 93 95 232 95 94 241 84 143 16 140 246
    36 89 138 18 13 135 250 119 159 31 14 149 100 125 12 88 220 64 48
    113 96 34 72 81 19 96 136 52 40 23 23 128 50 2 20 68 8 1 96 160 0
    193 168 32 128 96 128 70 115 65 50 60 169 44 15 208 24 110 104 146
    109 215 24 146 96 194 5 124 5 140 96 199 16 196 249 35 144 76 136 89
    3 35 32 14 137 76 31 160 72 78 104 210 70 192 136 150 160 200 140
    122 133 133 243 199 208 20 56 139 160 93 12 121 132 80 56 27 242 0
    205 17 80 172 8 32 8 182 151 64 16 160 55 89 0 0 105 146 32 209 225
    18 18 64 0 7 59 80 14 222 191 52 10 111 48 52 134 94 2 247 99 161 65
    114 230 45 170 104 145 1 46 240 167 230 128 36 242 36 32 0 132 135
    221 28 195 163 232 150 16 194 2 112 241 32 101 89 124 42 168 35 243
    91 29 45 34 203 4 16 40 52 162 37 172 17 154 221 205 194 200 31 17
    96 24 166 216 108 132 217 42 2 17 51 106 90 183 45 28 159 126 216 8
    218 138 80 2 76 165 40 10 72 0 36 36 134 129 215 11 18 82 102 197
    125 173 12 193 197 12 192 227 234 145 36 128 24 0 49 32 14 169 13 27
    224 72 198 36 194 3 195 136 54 192 104 140 234 133 12 243 199 144
    148 97 139 17 117 8 121 134 80 49 27 160 10 64 51 64 164 36 138 163
    23 151 32 80 34 149 237 128 8 1 129 0 209 229 42 129 32 2 39 99 34
    168 169 184 205 197 145 199 158 21 64 25 180 156 98 8 201 59 83 17
    18 106 210 51 77 20 158 123 208 8 151 234 34 168 35 152 221 197 129
    199 222 17 64 24 164 216 100 4 201 58 3 17 34 107 18 183 57 22 156
    107 80 8 214 170 72 48 56 96 33 12 81 17 105 8 52 8 159 19 0 48 132
    21 221 8 136 96 176 0 195 249 48 16 74 128 75 43 237 92 5 94 13 86
    71 176 212 210 230 64 243 113 53 255 200 100 120 106 233 231 123 47
    163 251 193 24 90 249 112 44 96 50 120 100 34 9 17 16 32 172 52 236
    23 7 192 18 6 84 69 0 0 64 160 0 194 129 33 176 96 128 6 51 105 48
    16 64 1 93 80 16 105 64 36 8 26 16 68 180 128 20 192 8 5 96 176 192
    3 217 1 19 74 4 74 22 87 82 228 130 138 50 158 136 134 246 157 167
    73 108 223 78 95 197 249 231 140 65 239 224 26 70 207 159 157 247
    189 85 221 78 151 183 2 34 170 48 188 130 211 210 253 115 161 203
    102 117 61 235 97 197 1 234 144 227 235 128 44 241 41 33 135 94 236
    153 142 54 156 143 150 246 132 151 192 108 95 75 79 71 251 167 188
    69 127 194 10 18 223 150 157 244 189 84 0 137 15 190 60 195 163 230
    134 9 216 34 176 243 32 64 200 42 19 73 2 171 10 61 233 166 186 8 16
    10 52 170 0 141 27 191 28 197 131 230 158 1 200 0 180 209 32 64 201
    58 19 1 3 170 82 61 109 166 154 72 16 8 180 170 2 34 6 137 74 3 168
    72 46 32 210 199 192 130 32 64 110 157 107 132 0 211 195 208 148 32
    139 128 29 0 33 128 1 32 7 129 68 75 160 64 126 96 66 66 208 8 20 96
    122 12 122 13 133 240 85 80 4 42 139 0 77 8 81 132 23 219 236 191
    138 16 156 174 130 213 144 167 241 44 215 74 79 99 189 215 212 73
    239 232 232 35 255 145 189 124 189 95 241 100 121 64 20 79 67 112 96
    96 229 8 19 17 17 48 88 156 80 106 105 54 240 14 81 136 0 48 97 139
    86 32 66 170 0 186 9 149 24 79 191 21 192 221 172 138 70 148 205 171
    235 133 14 75 210 241 144 112 154 59 24 4 171 30 35 147 236 133 142
    19 156 175 70 245 152 167 192 44 222 42 79 71 187 165 215 88 119 193
    46 15 223 214 157 252 153 220 131 77 7 157 148 134 173 119 84 192 66
    214 48 2 48 229 120 42 26 189 241 156 53 206 40 34 142 64 28 8 176
    220 1 156 25 253 20 133 67 254 22 9 88 80 183 211 40 96 217 26 22 8
    43 186 82 63 237 166 187 76 24 8 176 169 90 63 51 186 51 196 18 86
    173 77 90 237 46 215 32 208 166 187 157 65 2 139 16 239 179 244 10
    139 2 6 37 91 38 165 192 203 221 169 194 201 95 33 105 26 64 200 124
    128 89 138 3 49 18 50 73 151 29 4 145 109 241 75 210 130 104 48 49
    96 1 76 81 16 97 0 32 8 30 23 0 52 128 20 72 8 1 96 176 0 193 248 0
    18 66 0 70 34 38 100 129 155 220 39 138 202 22 179 89 82 64 200 121
    136 89 72 3 179 50 118 91 178 29 6 143 108 149 123 48 160 21 20 155
    231 146 38 47 27 48 163 75 210 213 39 8 104 55 95 57 190 49 208 153
    66 205 166 239 68 172 243 161 48 86 91 172 172 138 0 159 152 138 244
    144 167 69 206 251 75 102 213 125 231 196 67 175 96 240 32 239 189
    61 119 61 83 223 205 46 166 170 34 31 172 140 194 137 131 221 127 59
    66 183 87 253 231 108 1 31 170 233 199 143 157 182 247 161 64 38 140
    237 251 236 39 204 191 83 59 112 83 146 45 212 43 201 194 55 29 184
    126 75 162 47 30 212 244 221 216 208 172 53 173 121 105 246 167 251
    218 94 73 120 2 17 216 255 32 255 75 22 29 151 58 44 118 124 141 39
    236 221 219 227 193 106 34 64 197 96 14 105 16 53 44 118 205 75 7
    128 84 124 156 103 140 8 210 225 72 86 168 161 128 35 132 102 224 39
    20 236 145 141 55 156 11 86 247 135 151 192 44 94 43 221 7 123 181
    181 116 255 192 15 10 223 22 141 108 152 84 94 197 54 174 171 34 30
    172 141 146 139 131 221 111 57 66 183 83 253 231 72 1 11 234 251 241
    207 157 54 247 161 0 167 140 237 211 236 37 204 183 83 123 48 91 242
    44 92 43 201 194 53 29 190 126 91 163 47 30 213 242 213 248 208 223
    56 241 212 237 118 10 90 248 43 160 120 170 111 127 40 80 246 253
    149 96 10 178 9 157 186 245 5 166 55 170 7 17 25 91 67 173 18 134
    111 48 36 64 74 198 93 71 176 196 118 236 24 239 201 144 53 12 160
    237 170 128 46 166 33 112 43 48 65 73 77 159 224 88 75 104 116 76
    154 152 148 180 200 44 82 12 133 114 255 208 7 24 1 58 91 12 90 180
    88 2 94 165 42 2 59 16 52 36 134 231 207 7 2 82 118 213 237 133 12
    193 133 78 210 231 234 129 36 132 45 83 75 48 83 193 98 140 57 80
    173 8 50 224 140 151 128 244 38 53 255 136 1 65 161 192 148 248 10
    130 2 132 3 49 44 96 128 185 205 37 160 200 22 179 160 26 209 248 89
    138 89 200 115 147 2 118 219 144 157 193 207 126 249 121 90 130 127
    95 98 4 210 22 126 244 97 196 254 199 105 108 183 212 126 230 149
    238 204 155 180 236 50 111 133 129 47 247 250 92 71 128 135 149 140
    6 173 172 182 187 210 82 208 234 120 111 249 71 122 179 49 209 155
    192 157 50 223 196 136 112 177 36 118 149 236 1 151 115 214 47 67
    229 159 143 67 44 30 6 89 150 213 181 156 50 125 148 59 78 133 247
    231 238 212 86 64 56 27 242 32 204 49 80 168 8 38 8 182 215 32 16
    164 53 93 0 0 65 144 32 209 233 35 16 64 0 7 51 220 212 190 178 139
    100 63 175 180 19 135 17 220 247 43 75 161 83 249 179 50 197 26 98
    233 227 95 71 128 113 165 98 90 2 110 168 74 6 121 16 53 36 198 135
    205 7 2 80 118 157 175 133 8 210 193 64 213 227 171 129 32 128 36
    112 47 160 97 91 221 221 194 220 87 113 109 12 226 200 94 164 89 138
    146 28 159 98 127 177 15 94 149 124 219 142 218 252 113 48 8 169 44
    141 208 88 206 104 144 13 151 152 18 0 200 45 122 5 133 97 219 16
    196 105 43 57 88 8 89 146 83 32 76 165 40 10 72 16 45 96 130 205 207
    2 18 210 230 197 253 133 141 193 213 204 150 243 202 144 46 132 24
    20 105 48 56 97 84 77 99 16 112 32 100 8 19 17 0 48 88 140 64 8 41
    178 240 10 231 205 0 32 104 136 66 162 112 32 120 72 103 89 80 64
    121 44 244 42 10 25 148 52 186 156 198 0 12 114 228 192 87 216 0 51
    103 136 86 167 35 32 97 73 69 91 224 64 92 96 114 78 152 8 150 160
    122 140 82 141 133 242 245 192 22 25 131 33 77 140 123 132 80 48 26
    184 42 192 49 72 172 4 242 163 29 223 32 80 166 53 239 128 0 67 130
    64 209 225 42 139 36 0 39 83 120 32 112 72 109 89 208 64 121 104 244
    42 10 25 150 52 218 152 198 0 12 114 228 192 87 216 0 35 103 140 86
    231 80 12 207 255 20 194 111 48 52 134 66 34 113 99 161 65 114 238
    46 170 104 216 33 46 229 166 246 0 36 240 52 40 215 219 172 140 138
    20 156 173 134 244 144 135 64 204 127 67 110 213 249 231 204 65 191
    209 185 34 207 191 29 52 181 84 72 176 27 242 1 232 49 3 172 21 7 17
    190 215 40 88 129 51 233 0 18 77 186 97 193 177 26 75 128 0 7 106 70
    184 189 186 168 228 29 141 138 219 129 25 244 247 73 74 133 87 121
    19 51 73 219 49 201 147 223 126 144 113 133 114 106 34 65 204 73 20
    73 88 131 12 228 204 8 199 132 212 76 156 235 140 138 67 251 209 23
    248 129 186 18 132 118 244 99 32 44 188 44 157 200 72 206 252 144
    143 227 200 86 2 201 224 127 5 142 99 223 145 148 89 171 189 93 12
    88 198 210 191 19 174 114 192 62 228 169 64 72 229 44 214 36 84 182
    251 159 195 67 11 154 255 177 52 10 138 52 2 39 125 17 48 126 41 46
    91 176 72 238 96 242 34 223 152 246 160 170 29 254 1 133 241 135 208
    146 65 35 51 109 12 105 135 150 215 101 31 175 83 143 232 156 246
    146 247 72 108 189 175 95 85 255 231 229 229 111 255 48 66 207 150
    119 125 149 117 215 4 151 215 130 102 109 153 52 179 3 210 213 39 89
    111 119 215 57 190 49 212 153 66 141 170 223 68 168 241 161 48 105
    49 56 96 33 13 82 16 105 136 60 76 159 19 0 16 148 148 93 72 136 32
    208 0 227 253 32 16 74 130 74 3 64 57 17 97 32 204 83 16 36 136 42
    104 150 23 128 112 18 52 108 8 1 16 177 0 225 164 33 128 0 2 7 51
    225 113 17 64 20 79 67 48 112 104 224 72 18 17 16 48 24 156 84 106
    105 182 240 14 33 136 33 56 72 26 82 32 89 2 12 165 44 10 88 32 44
    36 134 129 215 35 18 82 226 197 125 141 12 192 193 0 194 227 234 145
    36 160 25 0 17 34 78 161 12 27 224 64 124 36 210 163 195 8 146 192
    122 141 238 5 12 241 69 0 150 227 171 17 109 8 89 132 245 213 173
    247 156 47 206 188 83 178 185 89 83 121 29 59 217 198 93 111 252 102
    89 47 235 219 197 52 217 123 210 2 106 34 71 205 73 6 105 88 55 12
    246 197 73 135 132 212 124 220 235 140 136 210 227 208 22 56 139 136
    3 132 38 244 16 219 31 238 60 131 67 240 132 12 218 96 247 211 160
    64 216 120 15 106 74 169 10 61 225 164 162 128 16 42 52 43 215 213
    168 174 136 116 30 168 22 230 137 143 213 110 123 66 215 215 249 231
    236 67 223 170 249 199 239 189 189 247 189 82 163 12 237 149 140 107
    141 39 222 246 130 147 144 60 87 43 201 103 123 141 244 124 247 192
    79 26 223 21 133 124 209 78 19 32 126 33 46 91 176 64 94 96 242 162
    203 152 150 160 250 29 254 1 133 241 103 152 150 67 43 147 125 12
    121 133 95 72 237 161 14 102 219 152 22 247 130 135 209 44 83 106 93
    205 49 215 142 84 255 160 201 79 207 180 181 125 16 82 16 128 151
    221 31 195 161 200 214 48 194 98 240 243 160 228 89 124 106 168 35
    195 75 93 149 34 203 22 48 40 52 164 222 133 228 164 159 2 94 168
    129 162 138 131 79 107 57 67 51 213 121 235 104 67 137 142 251 199
    143 31 54 246 57 2 5 204 111 223 4 246 111 182 116 82 78 2 241 99 48
    105 105 102 58 238 97 220 125 111 101 43 214 0 33 243 112 104 82 34
    71 76 106 82 168 88 175 12 242 224 201 198 164 246 110 221 239 136
    129 195 167 208 18 240 139 138 3 132 39 245 119 1 173 133 140 103
    173 11 198 251 155 19 80 60 87 43 201 7 123 181 28 81 247 0 93 14
    223 244 133 104 212 66 39 136 173 215 236 140 200 175 219 185 16 64
    240 41 220 11 201 70 115 29 146 120 203 177 12 26 245 244 220 200
    208 136 94 133 196 172 159 2 94 168 133 162 138 131 79 107 57 194 51
    213 121 235 104 1 11 142 251 199 207 29 182 118 57 2 52 104 137 145
    204 231 166 202 22 162 104 26 16 232 113 8 217 232 34 147 34 118 202
    50 221 7 159 45 145 121 88 138 220 156 188 254 139 100 22 172 150
    147 134 17 92 247 105 75 225 87 249 179 120 69 155 32 251 227 223 95
    178 113 173 34 39 142 141 215 236 173 204 175 90 187 16 88 240 57
    212 11 201 66 55 29 179 120 75 51 44 30 253 240 220 120 208 169 35
    48 46 27 109 157 224 88 207 104 52 76 130 216 214 164 136 40 86 13
    135 113 254 241 6 25 1 186 91 12 90 213 246 149 229 128 222 70 158
    107 3 249 153 255 80 60 28 3 221 151 93 181 184 107 89 204 57 8 173
    246 173 40 246 51 183 2 174 180 44 22 152 56 222 254 150 23 209 236
    119 43 221 101 253 165 173 229 119 136 203 91 239 148 132 44 84 87 3
    135 235 95 210 208 189 47 63 69 94 163 105 238 190 228 119 155 179
    133 151 152 167 207 46 111 158 139 167 198 188 125 90 18 64 165 19
    22 90 48 53 100 206 141 207 39 18 80 118 197 237 133 172 144 213 206
    246 231 138 129 46 134 41 80 64 50 121 96 34 72 81 16 32 12 54 104
    151 23 192 16 134 21 109 0 0 64 160 0 193 161 32 129 32 128 7 99 212
    201 157 229 170 14 95 188 160 242 130 145 215 55 73 83 7 85 125 238
    97 69 251 32 233 139 111 148 32 177 129 113 173 132 229 83 173 47
    207 189 83 251 151 88 211 125 220 47 93 70 125 62 185 244 125 130
    111 30 213 212 199 253 208 96 60 96 144 161 205 45 212 200 22 182
    164 10 135 249 67 10 217 200 98 19 10 118 219 146 223 205 207 61 243
    121 82 130 1 0 7 141 64 15 40 8 52 96 66 198 213 34 16 196 112 76 58
    141 1 208 85 76 4 34 203 0 44 0 49 144 1 32 5 129 68 75 161 72 126
    224 66 2 209 16 16 96 120 12 106 9 1 240 125 92 5 34 3 0 117 8 81
    160 67 48 91 197 98 24 40 64 172 32 114 224 221 151 132 242 38 93
    254 136 1 209 161 64 22 233 43 128 12 128 43 181 11 143 2 140 83 148
    42 119 53 5 76 198 168 130 166 196 108 43 130 204 199 154 4 253 36
    52 138 136 26 132 169 220 88 48 27 176 34 200 49 64 172 44 150 161
    159 215 32 80 162 53 237 128 0 193 128 64 209 225 42 131 32 0 39 99
    73 48 28 161 44 15 81 24 111 224 86 109 215 25 210 64 134 4 124 13
    141 240 213 16 196 251 33 16 108 136 25 1 180 70 93 255 44 43 71 184
    20 50 144 224 247 65 137 75 88 208 76 106 104 101 73 63 224 163 225
    20 52 249 20 32 149 189 125 105 178 131 219 252 86 32 248 98 147 25
    177 33 94 27 23 249 250 184 109 62 236 137 175 244 245 155 195 161
    72 50 25 32 32 12 24 16 33 72 52 237 159 23 130 144 134 21 205 4 133
    64 144 0 194 241 32 145 8 128 11 83 105 34 48 64 37 29 81 16 105 236
    52 13 11 8 150 182 132 68 228 12 140 96 164 128 67 249 37 51 66 132
    74 69 164 108 185 216 205 229 149 198 218 190 160 24 176 248 117 43
    201 122 115 19 110 103 250 48 85 26 221 59 209 121 86 202 58 233 115
    237 86 203 122 240 167 32 122 226 79 223 32 208 118 253 151 226 72
    178 8 223 246 237 1 39 55 187 34 129 106 34 119 200 75 66 41 88 51 4
    230 224 72 199 164 84 126 221 227 136 0 211 227 208 87 176 131 138
    35 132 38 241 104 48 56 96 33 13 80 16 105 9 53 76 159 19 2 16 132
    20 93 8 136 32 144 0 195 217 32 80 66 128 74 3 40 168 152 186 77 253
    144 79 154 49 33 24 174 152 64 138 137 27 195 17 22 106 218 145 13
    209 24 123 208 8 223 138 204 176 19 250 1 236 49 128 171 21 35 24
    174 215 72 94 129 51 233 16 18 77 186 241 197 240 18 75 130 1 135 98
    104 56 17 64 1 77 65 2 105 0 32 8 30 23 4 180 128 20 64 8 9 96 176
    192 131 216 0 18 74 0 70 38 106 34 103 200 73 70 105 88 163 12 230
    192 73 199 36 86 108 220 239 136 8 195 226 208 87 176 131 136 35 132
    38 241 72 48 25 224 32 77 81 16 40 12 38 12 159 19 0 80 132 20 92 8
    0 64 176 0 193 169 32 16 64 0 7 35 25 50 95 97 38 91 176 64 124 104
    82 226 223 28 132 160 182 21 238 1 133 241 37 0 150 227 35 147 101 8
    13 7 83 32 204 165 12 12 104 0 45 224 130 141 199 10 22 82 226 197
    121 133 13 195 213 64 150 58 138 16 44 4 120 22 37 168 152 187 221
    205 240 200 158 49 96 26 244 216 108 128 217 106 2 17 39 114 90 55
    15 159 7 127 216 8 219 130 60 237 122 111 87 159 251 248 87 0 126 2
    115 201 60 52 122 232 19 106 194 177 157 191 127 205 133 4 127 187
    82 170 104 56 56 112 33 141 81 22 105 8 52 76 159 19 2 16 132 55 93
    8 136 104 144 32 195 217 48 16 74 128 74 11 87 193 169 174 158 68
    143 136 2 245 137 139 213 239 89 66 93 197 121 255 219 67 223 112
    249 36 143 252 181 51 177 112 85 18 173 165 160 14 125 48 32 238 146
    229 215 39 147 91 38 229 125 175 172 193 245 8 208 227 239 144 172
    240 37 81 56 34 115 64 111 89 240 64 123 36 240 170 10 157 212 48
    250 156 199 1 12 114 236 208 23 88 1 59 103 140 86 135 1 156 21 249
    188 143 65 63 86 41 88 116 183 49 160 96 209 26 46 24 171 184 81 31
    232 142 53 84 24 8 128 41 49 164 111 65 212 203 161 103 86 225 66 19
    19 156 54 32 121 46 19 21 191 248 117 31 111 15 149 37 101 8 214 238
    33 32 101 73 77 31 224 72 79 96 240 72 130 152 148 164 200 12 82 12
    133 242 247 208 23 24 129 42 91 12 90 164 115 193 236 165 140 71 157
    175 70 117 138 135 145 44 94 34 77 71 121 213 222 121 245 145 237 15
    223 84 165 8 208 222 111 132 173 179 172 38 141 157 22 255 147 211
    209 108 218 43 221 71 125 183 188 96 239 2 237 10 255 212 148 121
    208 96 17 48 63 41 46 95 176 72 206 104 114 42 214 152 54 160 170 13
    126 1 133 241 55 16 151 201 35 51 77 8 89 135 161 116 81 73 116 15
    67 120 80 106 112 76 83 17 144 49 88 140 22 106 233 182 113 30 37
    136 97 32 121 185 82 161 49 32 110 169 76 95 224 72 206 96 224 11 18
    216 118 32 232 140 114 133 141 243 223 80 85 9 139 57 93 8 122 134
    99 56 40 25 109 157 208 15 74 249 180 93 162 24 86 32 137 34 90 13
    143 106 214 17 142 89 144 56 88 12 90 94 82 48 19 178 35 192 48 64
    173 0 162 41 46 214 32 212 162 49 239 128 3 67 130 225 145 240 10 11
    32 4 39 55 25 48 62 161 46 75 176 88 127 96 86 42 223 152 178 32 50
    157 126 1 133 241 39 208 212 33 35 3 109 8 41 3 105 56 17 112 69 221
    112 7 233 96 100 8 58 152 4 182 128 38 224 8 13 120 240 0 7 249 16
    51 74 4 74 14 104 54 120 96 112 15 83 16 48 44 124 237 151 7 130 16
    150 220 197 40 136 176 208 14 230 237 33 160 104 130 74 51 96 2 21
    141 13 67 128 8 198 24 210 98 192 242 160 230 72 212 238 128 9 195
    207 145 132 178 235 30 22 8 52 37 73 32 84 161 110 11 121 24 111 96
    86 13 223 129 18 116 34 140 126 13 133 240 213 208 212 56 1 0 110
    140 9 0 104 34 24 96 32 13 88 16 41 172 60 77 159 3 2 18 132 197 205
    12 136 32 192 0 194 253 33 176 74 130 74 3 80 50 26 224 34 12 89 16
    32 44 38 13 151 135 2 80 166 21 109 0 0 65 144 0 209 161 33 32 40
    128 7 115 57 32 46 169 77 75 176 72 198 96 224 11 18 152 50 32 232
    140 122 129 13 243 215 16 85 1 139 57 121 8 122 130 69 148 149 243
    172 106 69 157 102 123 131 112 215 55 73 107 193 86 108 58 57 68 251
    32 205 162 119 84 168 113 133 35 68 160 157 242 168 68 69 140 138
    187 129 24 215 247 73 122 129 87 125 24 27 73 235 49 201 130 127 252
    144 113 133 35 24 32 60 169 46 91 144 72 86 96 210 171 223 152 146
    32 122 157 254 129 12 243 71 144 208 193 43 153 117 12 61 3 34 34 5
    201 104 22 232 88 46 44 226 196 193 134 148 212 204 12 251 140 137
    210 243 208 7 249 171 144 16 128 118 244 89 18 31 33 6 91 48 16 117
    104 210 234 223 140 128 96 54 157 238 129 141 240 101 192 212 227 33
    129 101 136 45 5 131 204 37 219 141 102 133 175 84 91 202 18 240 48
    60 111 201 70 58 138 121 93 123 247 189 62 222 86 152 88 240 44 98
    34 73 73 105 21 200 88 138 12 224 200 128 206 132 240 204 28 234 128
    140 67 242 208 23 249 139 185 83 0 110 164 88 18 204 165 34 10 58 16
    52 164 194 229 207 39 2 208 118 213 237 164 8 208 197 70 214 231 234
    128 44 160 33 81 0 50 123 72 74 81 184 72 230 0 244 224 209 222 164
    176 238 157 238 128 13 227 167 80 23 169 35 137 65 128 47 161 247 87
    229 5 143 31 143 168 92 246 130 207 195 108 149 175 93 196 251 239
    233 244 125 140 37 122 205 150 111 124 84 116 25 34 62 41 14 91 176
    72 230 104 242 226 223 156 18 32 238 157 238 129 140 227 199 16 210
    193 43 25 101 8 45 133 91 2 14 173 8 14 73 24 52 164 194 197 215 35
    18 80 212 197 125 141 12 208 209 12 212 227 235 144 40 164 48 80 67
    34 3 201 41 20 168 72 175 12 210 196 201 198 148 244 204 149 255 140
    141 195 227 208 151 240 139 152 2 132 39 244 97 32 44 185 44 157 192
    72 206 248 144 13 215 200 82 0 201 36 126 5 140 99 219 16 212 241 41
    61 88 8 91 134 33 48 119 73 111 91 176 72 95 224 112 42 72 152 244
    164 250 12 98 9 133 243 255 208 23 24 3 34 93 12 91 135 60 32 148
    225 141 107 84 200 23 182 164 11 195 185 65 142 89 200 107 24 26 242
    89 144 203 217 133 55 227 120 92 130 96 38 120 96 116 15 115 16 113
    12 124 8 19 3 134 20 30 204 68 44 136 176 192 78 230 156 32 0 66 138
    66 33 208 49 91 224 50 72 19 80 52 4 110 173 87 151 0 80 54 149 109
    96 64 17 177 10 241 165 33 129 32 130 39 115 161 117 81 65 116 15
    102 56 112 104 112 92 82 16 144 49 28 12 86 110 233 244 89 31 36 136
    33 32 72 138 82 161 65 56 26 114 33 140 80 86 169 136 34 76 191 155
    0 144 132 55 108 0 13 105 146 32 195 249 16 50 72 0 11 11 77 121 25
    82 129 253 86 148 233 89 37 76 158 210 77 190 128 19 252 90 7 33 186
    97 131 249 0 123 74 19 203 23 119 4 236 197 140 114 204 136 83 179
    134 154 195 120 223 239 89 196 120 187 189 69 239 128 138 26 205 55
    183 253 216 4 208 114 72 228 18 70 91 48 52 164 134 141 215 7 2 80
    118 213 109 230 104 21 209 14 241 165 43 144 32 163 38 113 208 0 31
    165 4 74 65 48 36 198 130 18 215 35 0 91 96 132 108 168 105 197 113
    12 209 227 242 16 32 160 36 96 180 93 222 247 182 107 182 230 220
    162 154 50 87 120 37 171 187 119 213 99 117 245 8 174 170 199 111 55
    237 123 221 131 50 109 83 238 87 135 110 224 165 132 234 2 107 203
    53 208 252 249 19 226 72 147 24 253 179 252 129 9 99 187 102 170 21
    220 28 253 40 15 95 184 164 58 178 96 215 23 1 75 199 85 125 107 233
    197 89 29 224 235 107 148 120 179 1 19 149 93 30 179 134 235 150 230
    156 178 56 54 215 56 33 11 171 115 206 115 101 237 24 62 168 131 111
    55 253 121 137 155 201 115 24 96 32 173 80 22 41 9 61 93 159 19 0 24
    132 5 76 64 12 44 144 0 194 249 32 80 72 131 203 3 180 173 156 177
    148 235 131 207 86 183 168 19 147 57 97 9 249 194 10 177 62 249 73
    62 233 135 143 117 241 89 212 130 34 34 103 73 73 86 169 88 174 4
    228 192 72 135 36 244 236 157 227 136 8 211 243 208 23 248 131 8 3
    128 102 244 220 94 222 180 34 58 52 16 232 134 147 243 79 242 163
    219 163 245 236 34 44 197 129 72 210 227 107 147 164 241 41 3 189
    141 144 120 189 191 70 191 215 150 172 20 227 113 171 245 209 98 140
    46 255 4 120 159 171 223 5 22 154 252 216 12 116 229 157 247 141 111
    70 172 202 178 168 8 215 121 73 27 137 214 120 99 121 98 219 56 233
    219 197 60 216 123 210 34 173 207 144 251 181 189 71 190 87 54 44 20
    227 99 179 229 81 106 8 126 255 124 120 191 170 223 21 53 154 253
    216 76 238 198 224 222 205 52 79 159 19 31 237 80 73 227 220 222 89
    202 35 154 122 70 235 227 63 190 214 76 146 243 244 44 3 49 127 73
    111 91 176 90 236 72 126 110 28 216 166 160 174 25 246 0 133 179 182
    192 22 47 34 139 77 8 107 215 17 2 133 37 20 30 224 50 124 228 226
    196 203 40 150 194 220 68 236 37 173 240 101 28 132 243 195 17 73 44
    89 68 76 166 165 179 173 46 77 191 23 191 151 88 215 97 88 239 77 70
    125 63 186 64 203 176 237 26 223 244 134 253 148 96 89 2 140 165 44
    24 72 16 40 140 146 233 207 43 146 210 130 197 109 13 12 64 193 0
    194 243 235 145 36 160 91 1 87 176 169 186 90 228 185 200 62 85 65
    151 213 254 122 104 247 11 51 149 150 86 190 83 221 39 155 108 148
    67 33 214 106 58 99 72 91 86 121 94 51 68 230 141 9 135 2 212 124
    157 167 140 137 218 243 216 87 235 145 137 51 132 38 248 188 78 133
    241 173 107 71 154 23 190 148 242 195 37 129 143 77 212 206 122 41
    228 109 190 140 210 229 181 247 253 20 225 124 132 148 250 141 119
    80 136 151 31 165 16 74 115 104 223 217 146 232 50 58 71 75 149 219
    243 81 95 178 77 252 2 197 158 172 183 188 111 199 188 222 254 152
    21 246 120 91 11 129 98 108 39 253 97 123 63 233 83 255 149 152 123
    221 83 89 0 140 165 32 88 88 16 40 200 138 205 223 47 18 210 182 197
    125 141 141 64 193 2 194 255 234 145 12 166 11 17 28 109 138 163 148
    171 226 202 22 160 142 2 211 227 97 0 121 238 10 184 58 185 73 62
    237 135 175 117 177 123 24 130 253 68 172 101 141 111 71 184 81 242
    166 9 83 61 83 59 153 196 121 47 232 98 249 138 235 251 197 20 227
    120 86 98 45 132 173 101 156 79 199 186 82 242 134 8 211 125 17 43
    89 196 121 47 232 240 121 12 239 235 197 20 227 248 84 98 41 176 56
    59 13 253 144 3 206 121 161 29 190 152 86 32 137 35 90 5 151 105 242
    49 197 89 18 123 88 8 91 222 87 16 135 215 141 38 108 153 163 187
    131 82 208 114 93 255 97 214 120 186 57 193 155 192 153 186 223 68
    136 113 161 52 82 34 23 220 42 194 185 72 172 4 214 162 76 199 160
    214 102 253 239 128 0 195 162 192 145 32 11 139 7 132 39 245 17 48
    127 97 78 91 176 72 110 96 242 34 215 156 160 32 42 157 126 1 133
    241 167 80 84 1 35 1 109 8 45 131 115 32 72 168 73 13 104 64 57 100
    226 143 66 11 22 80 248 141 123 133 8 82 209 64 213 40 137 56 41 0
    122 18 253 228 169 70 157 93 71 184 195 226 172 8 83 121 91 182 89
    192 80 106 237 39 120 190 123 223 133 60 91 251 90 102 17 59 126 105
    6 159 176 70 110 96 254 226 155 156 134 32 174 61 238 193 132 185 37
    88 103 237 35 3 101 8 39 255 124 141 165 101 141 94 69 186 67 182
    174 8 211 57 81 175 9 228 121 42 72 232 241 136 235 251 69 20 194
    248 84 98 161 135 12 169 152 231 25 175 22 125 136 149 149 38 10 65
    205 11 11 149 190 8 109 55 237 135 186 245 152 0 133 216 105 56 56
    83 77 221 113 7 235 101 101 29 58 153 22 48 128 46 66 12 151 120 240
    81 71 57 16 51 74 4 202 222 45 188 156 69 140 79 197 191 86 186 166
    76 211 49 65 43 9 84 120 40 41 232 121 8 111 139 117 52 200 248 216
    48 100 206 213 209 237 63 103 179 159 191 54 93 194 37 199 207 197
    102 175 62 48 116 123 162 15 30 213 118 154 249 212 116 84 149 189
    180 141 127 148 232 198 254 138 15 214 124 91 43 129 86 236 99 236
    99 187 136 251 195 69 63 192 122 20 87 100 142 205 89 236 112 68 143
    82 251 53 248 193 110 205 123 201 214 46 146 191 98 239 48 14 179
    247 253 144 249 220 53 117 49 141 131 190 11 163 136 14 241 187 238
    215 100 200 34 95 68 104 118 153 97 253 0 152 4 47 116 204 43 129
    116 145 84 23 191 10 38 175 104 180 130 226 194 245 118 33 107 126
    117 122 235 97 197 25 111 177 162 202 0 9 113 33 176 44 161 112 72
    221 213 65 235 67 53 172 8 146 209 92 60 217 154 82 184 26 106 122
    149 79 158 149 127 211 10 246 162 102 170 165 215 237 30 109 190 155
    191 6 88 198 225 208 206 193 102 123 30 178 88 251 176 15 26 213 246
    130 249 212 36 229 221 217 186 238 108 71 190 19 94 109 29 86 243
    107 93 83 78 35 110 112 22 216 50 116 174 101 44 186 251 208 115 237
    120 58 50 13 237 241 0 234 113 165 25 190 216 90 42 129 35 120 21 22
    109 186 49 205 217 16 121 192 13 3 194 237 125 56 98 161 252 87 148
    233 78 47 29 159 26 75 58 129 66 76 94 255 36 248 34 227 249 4 120
    200 211 194 66 82 34 95 92 10 210 185 72 172 132 198 162 77 198 164
    118 102 245 235 128 0 195 167 64 147 163 11 139 33 128 45 117 68 178
    189 243 168 104 21 156 162 191 135 120 215 119 201 91 7 86 108 58 18
    64 235 48 201 163 119 124 128 241 133 97 90 34 201 229 64 6 105 16
    49 164 70 197 221 39 2 80 118 221 61 140 8 210 209 66 213 175 138
    128 42 160 32 112 49 48 126 73 78 91 176 72 254 224 242 42 91 216
    182 160 186 29 234 1 133 243 175 208 20 72 35 51 77 8 103 135 106 34
    71 204 73 7 73 88 167 172 230 141 65 199 0 86 76 220 239 140 8 67
    203 208 87 184 129 184 50 132 102 96 35 41 122 88 73 148 185 79 171
    1 236 128 41 134 164 244 76 191 242 136 139 11 246 209 23 125 146 58
    83 130 102 188 118 205 1 106 153 36 78 172 33 16 169 73 83 127 93 83
    221 211 93 238 122 3 216 224 187 216 133 62 177 243 226 2 80 48 89
    160 34 72 25 16 40 100 166 173 151 23 2 82 38 213 125 0 5 65 177 0
    209 225 42 161 40 128 7 83 25 48 30 169 47 91 176 72 238 232 146 43
    223 152 18 96 162 5 110 1 133 241 159 144 208 227 43 19 76 12 25 7
    212 158 158 182 150 107 150 252 214 226 154 250 247 249 41 3 63 247
    236 35 125 225 13 46 248 199 109 21 237 251 153 11 82 50 87 204 75 2
    57 88 181 4 230 239 77 199 32 84 118 221 235 128 0 211 131 192 87
    160 3 139 35 132 38 112 105 35 24 32 48 13 90 16 41 172 252 77 159 3
    2 144 148 205 205 76 12 48 192 2 226 253 33 177 66 130 74 3 109 245
    157 163 173 125 85 188 66 250 173 8 214 113 75 59 129 70 108 106 89
    96 251 48 233 211 117 61 152 123 138 99 24 50 63 105 9 87 185 88 230
    32 230 2 217 142 48 32 236 157 106 129 141 243 243 80 213 161 139 9
    97 0 47 176 84 16 149 237 170 110 5 27 172 186 131 112 215 55 1 123
    167 85 125 32 57 197 243 0 129 226 107 20 160 113 5 49 25 34 47 105
    41 31 216 88 110 44 242 197 203 142 18 32 204 157 238 133 140 243
    247 144 213 241 171 145 97 0 47 150 0 34 62 109 104 151 185 88 230
    160 246 64 208 206 48 34 204 125 106 129 141 243 251 80 85 170 139 1
    65 0 39 176 75 34 15 109 41 23 72 88 119 232 246 192 201 206 16 228
    220 221 238 141 141 242 255 208 213 178 139 136 106 128 42 20 73 34
    24 164 32 12 88 16 41 12 174 77 207 3 2 210 150 197 109 12 12 0 193
    2 194 253 32 145 10 162 10 3 84 176 157 241 168 108 65 159 42 251
    130 56 151 55 72 122 129 215 124 16 27 72 243 0 201 242 127 84 128
    96 135 123 103 55 129 133 156 47 142 152 74 233 155 206 209 96 221
    46 93 68 124 255 157 112 253 202 44 30 175 244 141 255 208 117 33 48
    126 65 110 91 176 72 126 232 116 106 18 152 214 164 186 12 66 9 133
    240 175 208 22 24 3 35 77 8 91 133 97 92 188 109 44 124 85 191 75
    250 190 44 247 112 195 122 129 86 124 40 205 96 243 1 215 255 117 63
    88 248 88 43 66 50 87 205 74 18 41 88 55 4 226 230 72 199 164 212
    126 221 235 136 1 211 167 208 22 32 139 138 35 128 38 180 87 16 158
    133 130 54 60 128 171 179 135 150 205 34 79 238 39 213 232 150 149
    193 157 192 152 227 95 71 168 113 169 20 9 134 156 247 141 221 101
    191 86 247 4 20 255 97 202 175 1 74 32 28 119 120 123 55 239 223 117
    113 154 220 217 232 37 116 156 101 172 47 197 186 86 250 38 28 211
    113 219 43 29 68 96 46 249 240 121 10 111 139 101 52 202 249 208 176
    156 13 78 243 151 139 98 232 212 160 142 2 243 97 35 65 121 230 74
    120 40 241 13 62 254 135 135 81 162 251 24 2 89 4 137 164 48 88 74 0
    48 200 218 105 223 43 210 240 178 205 125 141 13 16 197 2 242 253
    170 129 38 166 27 1 60 160 156 225 141 75 80 200 71 180 164 10 194
    185 65 14 217 220 232 16 10 99 91 144 219 210 133 119 179 122 94 2 8
    34 108 169 12 75 216 72 199 100 210 171 203 140 18 32 78 149 238 129
    140 227 199 144 212 113 171 185 119 140 28 0 40 32 113 73 69 91 224
    64 113 32 116 10 11 5 148 180 120 156 130 8 9 242 100 200 23 201 128
    33 99 142 94 164 244 54 105 101 16 46 75 48 48 110 231 205 211 7 3
    81 52 156 29 174 233 150 113 14 209 171 160 128 32 225 38 112 205
    121 17 34 161 236 86 148 169 89 43 92 158 19 73 218 132 35 204 82 87
    0 154 32 227 249 0 66 74 83 139 19 40 54 121 65 114 11 107 16 113 36
    124 140 19 5 144 16 62 156 6 44 160 176 116 78 103 143 33 32 101 130
    70 176 83 34 15 201 40 22 200 72 175 40 210 196 194 142 148 224 204
    133 254 141 141 193 243 208 145 184 139 146 0 0 41 116 56 48 10 168
    77 69 145 72 198 64 228 11 22 209 34 4 232 136 91 1 8 99 218 144 85
    0 139 59 91 12 122 130 45 97 51 48 173 205 69 196 171 21 36 8 158
    213 89 159 136 0 89 94 74 33 242 177 195 217 4 122 194 93 214 98 67
    32 30 200 73 22 104 88 229 64 230 2 72 130 48 244 104 141 106 136
    141 211 151 192 23 56 130 9 43 128 42 4 104 57 184 111 169 92 85 21
    106 233 174 12 191 57 67 114 134 119 236 0 133 104 243 2 231 253 116
    59 200 122 143 27 89 50 22 165 47 27 48 88 127 160 210 238 207 152
    130 228 54 213 238 1 132 241 31 220 148 226 1 18 110 140 9 7 26 48
    118 233 75 67 249 72 39 36 246 2 88 159 32 100 106 157 106 128 8 243
    243 208 213 168 139 10 123 0 38 178 100 34 237 165 140 106 129 138
    66 183 130 139 211 41 81 10 73 196 105 17 24 96 239 0 205 130 229 53
    197 120 84 98 18 48 126 73 42 67 185 88 175 40 246 162 208 159 160
    100 106 29 126 136 129 243 247 208 85 184 171 144 89 0 103 179 120
    49 105 101 160 110 77 55 48 107 118 141 147 39 0 25 52 148 85 172 25
    208 81 12 227 239 240 132 232 240 194 115 52 97 14 214 28 203 99 104
    198 132 198 10 115 67 42 67 120 224 106 248 8 225 59 44 217 131 133
    81 161 10 116 34 80 34 121 164 34 72 25 16 40 232 130 233 215 23 66
    114 38 213 125 129 8 64 133 0 209 225 43 177 36 128 7 115 167 140
    204 31 141 94 206 170 218 242 16 86 243 120 191 163 153 102 48 47
    245 96 94 191 46 127 207 52 221 124 217 148 98 34 108 93 104 209 137
    72 170 180 228 168 193 198 198 114 205 252 234 128 10 67 234 17 23
    248 163 61 81 0 102 164 104 169 157 101 141 94 85 167 195 176 174 8
    243 57 80 50 128 246 104 72 9 105 243 8 235 255 213 17 194 186 92 42
    99 184 41 82 77 253 209 0 235 125 165 29 186 156 94 190 136 36 113
    28 147 110 242 33 7 89 16 114 194 13 86 246 99 160 233 68 13 93 201
    11 11 181 164 8 146 28 84 50 136 148 113 29 8 110 240 144 159 153
    153 61 193 8 82 238 48 33 248 204 13 95 82 72 71 164 172 10 2 153 68
    18 216 212 104 80 14 35 219 144 251 220 5 63 115 42 86 6 76 140 213
    150 222 233 119 166 151 247 66 59 254 113 227 79 3 226 42 14 113 250
    107 235 108 30 85 10 186 253 132 123 88 54 120 96 178 106 93 23 48
    38 62 253 31 7 131 25 54 149 205 34 184 144 128 14 242 229 48 181 36
    241 135 115 75 34 5 173 104 94 232 72 126 232 210 64 220 142 144 240
    240 69 126 141 133 81 239 80 149 50 171 144 0 4 27 37 69 0 212 69
    139 62 4 136 111 178 166 68 206 34 197 239 71 68 232 62 133 225 223
    192 140 186 71 22 138 249 73 36 87 96 142 164 138 86 92 128 160 242
    130 7 85 246 87 122 227 197 120 223 13 67 191 64 217 235 207 5 169
    115 41 86 119 163 200 164 202 48 94 152 3 226 152 207 65 234 91 194
    87 205 181 215 204 82 207 130 190 68 173 189 173 247 26 148 90 50
    103 173 110 11 120 88 127 164 210 239 77 204 112 192 126 221 239 5
    132 243 255 208 212 99 139 138 119 140 36 87 64 154 157 247 170 104
    53 151 170 191 19 245 215 55 192 90 135 87 109 16 48 88 235 0 205
    243 119 196 160 224 133 123 145 105 58 107 24 135 152 69 118 0 226 2
    179 136 16 32 236 189 121 193 204 171 69 30 241 237 42 17 97 130 169
    8 165 100 109 69 228 79 239 184 80 226 52 202 83 101 149 47 27 220 2
    110 225 244 125 10 101 10 101 52 101 251 82 240 213 68 151 109 136
    38 77 56 180 130 194 64 211 115 1 123 89 212 120 170 105 197 81 8
    225 170 199 16 160 241 32 32 72 178 189 247 168 232 49 23 170 191
    151 113 183 183 200 90 135 87 109 16 18 72 235 33 205 163 127 253
    128 192 135 123 109 172 177 112 145 205 87 187 249 86 36 9 255 127
    75 51 145 33 88 40 102 33 176 11 235 223 5 60 210 96 66 98 48 33 122
    73 79 91 178 72 195 96 252 42 2 152 166 180 120 156 194 64 13 179
    246 144 55 77 1 59 115 14 126 134 20 4 238 103 134 98 229 9 112 179
    211 50 211 57 24 11 123 214 109 179 56 244 13 2 200 163 255 69 229
    115 247 162 40 48 18 152 79 205 145 72 206 180 132 8 174 209 98 134
    201 112 235 1 2 99 218 209 217 16 1 63 90 12 11 162 68 178 189 228
    168 14 85 152 162 191 164 13 215 119 73 90 135 85 109 24 10 65 251
    16 203 163 101 60 136 240 7 115 40 48 97 69 112 10 107 16 49 36 118
    164 25 3 144 20 122 204 23 172 33 146 244 78 102 174 160 128 111 128
    66 240 116 180 214 215 214 66 103 248 155 182 70 46 80 243 163 87
    113 116 113 58 33 209 137 174 108 174 197 182 175 248 82 163 99 32
    110 141 104 95 104 72 127 232 246 72 64 206 150 116 216 204 126 141
    133 243 207 208 22 58 131 139 78 128 122 149 25 50 126 65 38 27 176
    64 126 96 118 230 223 152 150 160 62 29 234 1 133 241 53 208 6 139
    35 3 109 136 75 133 16 34 126 97 14 91 177 64 118 44 242 162 211 8
    148 32 62 157 238 129 140 241 101 16 133 195 35 17 101 8 103 164 114
    34 45 173 77 75 72 72 199 236 214 235 195 205 82 130 104 221 239 129
    142 115 207 145 215 97 169 185 117 140 28 66 105 47 145 164 113 28
    90 18 33 68 106 77 143 7 2 144 148 204 196 76 141 16 208 10 230 253
    0 0 42 134 74 80 253 241 153 230 174 89 87 184 66 248 164 40 215 113
    203 50 145 212 108 106 77 101 251 34 251 197 101 61 224 250 6 99 98
    50 90 200 75 20 57 88 163 12 228 198 8 199 164 84 110 157 235 128 0
    67 186 208 23 32 139 171 35 128 46 181 253 156 245 151 247 106 55
    172 26 247 42 255 79 245 239 223 179 78 161 62 113 241 169 186 46
    238 101 118 222 255 213 243 229 125 24 34 161 189 86 148 233 90 61
    93 159 211 75 178 133 99 76 94 255 36 216 34 227 217 36 56 200 211
    202 3 80 50 51 168 79 73 177 88 239 104 210 107 14 217 32 100 38 157
    238 1 128 115 135 208 213 32 3 43 103 12 37 231 89 0 151 118 13 220
    80 39 253 97 131 24 246 248 8 242 128 54 248 1 13 233 211 135 147
    247 80 19 66 14 217 14 240 228 31 238 28 207 67 72 198 132 239 26
    115 81 41 80 120 144 106 234 106 39 123 31 217 129 129 25 17 11 116
    98 176 228 25 232 29 71 67 232 87 4 160 26 18 217 41 0 216 152 72
    227 107 39 248 31 177 160 129 127 113 41 118 162 110 162 165 144 141
    17 205 143 142 183 130 159 198 236 94 206 65 70 233 21 30 75 223 177
    137 19 221 125 134 76 212 68 69 217 149 164 136 15 78 186 174 178
    138 76 215 115 73 10 129 69 120 107 65 65 219 40 169 138 79 60 200
    114 1 56 18 50 54 124 106 135 185 88 166 140 242 224 200 206 228 34
    238 253 238 129 138 227 139 65 80 176 11 139 65 0 39 177 85 8 149
    101 136 38 68 26 100 138 130 64 211 115 1 123 65 212 108 170 105 193
    211 8 129 170 229 16 160 241 32 32 184 241 57 108 93 79 83 232 83
    172 164 24 18 217 68 48 216 216 196 98 106 39 248 31 251 205 5 63
    112 42 86 34 76 176 181 101 168 77 89 152 34 188 162 12 215 55 64 18
    133 84 109 28 9 64 249 1 201 136 101 124 2 160 7 114 94 170 140 223
    171 208 28 174 179 151 192 179 233 238 204 207 231 251 161 144 62 74
    238 241 204 50 223 235 165 116 175 206 64 58 59 164 32 204 73 18 160
    64 130 77 151 135 0 82 132 245 125 133 9 73 145 0 193 161 42 16 0 0
    7 48 76 168 149 223 137 217 37 174 155 211 162 24 232 247 76 207 129
    114 234 152 51 104 235 241 13 122 85 90 130 252 133 232 120 33 165
    165 12 74 1 8 34 240 130 9 211 37 65 10 8 212 105 17 9 98 209 0 201
    161 69 53 224 40 86 114 1 48 123 72 75 81 176 72 230 68 244 162 73
    222 164 52 110 157 234 128 133 227 183 208 23 233 3 11 105 0 47 247
    26 48 118 201 75 83 177 72 39 36 246 34 200 159 4 196 106 157 239
    128 8 243 243 208 151 232 139 26 127 8 37 178 115 34 22 201 77 79
    249 72 239 96 246 74 94 158 54 116 232 140 122 12 133 243 195 208
    215 184 131 51 1 12 123 135 33 50 111 169 78 31 232 88 46 36 210 207
    213 141 16 208 110 141 251 141 133 243 247 80 23 33 163 168 101 136
    53 240 214 182 213 165 158 15 55 248 123 250 178 238 87 116 4 55 55
    85 108 50 228 241 141 206 253 162 101 150 165 250 7 119 92 178 156
    182 170 0 25 189 174 253 135 181 255 247 74 82 167 87 253 17 18 65
    155 113 216 227 127 255 168 192 133 91 25 32 118 65 1 31 168 64 126
    32 246 70 217 10 148 164 126 29 238 140 141 241 117 208 7 251 11 1
    75 4 107 148 176 113 123 105 30 91 146 72 86 96 240 42 19 156 36 160
    250 156 206 99 76 163 197 30 115 197 35 59 117 10 126 134 82 48 94
    156 11 217 144 74 142 240 160 171 46 221 102 130 43 121 234 0 6 99
    138 81 146 97 1 59 84 8 7 135 48 2 23 205 108 83 33 88 87 164 226
    226 67 134 164 228 124 220 170 128 8 243 107 216 21 242 3 18 19 140
    100 228 24 34 55 161 44 79 97 80 119 44 210 34 223 13 144 96 124 149
    110 129 136 241 97 144 213 243 33 16 100 136 36 32 50 34 47 165 76
    31 232 88 62 164 194 207 71 204 80 192 124 205 235 133 140 241 239
    144 151 99 139 49 37 12 20 226 9 48 118 205 43 11 169 88 254 172 242
    166 216 211 164 70 122 92 110 136 0 227 235 208 20 42 35 146 95 136
    33 177 97 34 15 140 108 91 232 88 126 232 194 72 213 198 208 242 112
    204 122 9 133 83 207 80 148 35 171 169 0 0 59 133 43 35 99 69 71 30
    233 80 117 100 124 230 88 23 132 180 124 204 18 140 129 242 101 204
    7 58 130 130 111 134 98 245 24 34 46 97 40 15 233 64 62 44 242 1 211
    14 16 0 220 13 110 140 8 240 65 16 197 251 171 144 64 8 71 162 16 2
    221 237 52 11 99 24 85 36 102 230 211 35 128 80 86 220 38 40 168 208
    97 30 196 166 33 0 50 168 68 96 81 48 26 168 9 21 88 88 231 8 240 13
    139 203 2 240 76 157 238 129 140 99 223 80 209 241 139 56 90 128 42
    6 253 74 136 164 12 8 82 136 226 228 174 9 71 169 83 82 96 196 108
    103 76 103 207 10 219 225 69 61 33 234 94 66 41 58 97 89 65 159 225
    87 113 36 116 206 43 133 132 180 108 190 130 136 137 250 228 200 7
    88 16 34 99 140 102 236 102 174 194 222 234 80 30 232 187 183 140
    171 104 231 239 158 127 223 161 146 2 67 142 241 122 22 207 239 135
    246 39 228 89 48 59 112 33 221 176 64 234 200 50 108 190 220 102 176
    164 53 236 1 133 97 178 80 209 217 35 50 72 4 75 151 114 32 150 188
    10 195 56 72 183 176 226 161 65 227 32 118 249 245 235 128 12 83 139
    93 154 178 207 55 16 168 36 6 119 164 130 164 196 3 110 232 83 226
    218 207 112 232 210 0 89 236 121 175 141 83 205 138 60 46 205 188
    173 110 88 4 112 50 249 109 118 11 82 56 119 160 122 109 87 57 192
    80 18 204 103 44 141 114 201 30 254 254 101 34 124 170 82 3 33 32 15
    169 108 11 232 72 38 40 242 203 213 143 144 80 104 141 127 141 5 243
    195 80 87 41 163 160 5 136 58 144 48 102 120 41 26 75 146 104 68 32
    240 171 211 28 130 33 122 157 204 227 76 179 197 28 240 193 33 185
    117 10 46 131 70 160 188 154 139 192 24 207 138 53 132 19 236 254 78
    90 193 215 249 145 30 75 218 241 155 2 223 127 144 64 175 142 83 168
    156 27 137 205 80 142 202 49 164 24 166 186 70 58 129 199 104 17 30
    107 219 113 217 186 93 127 144 72 139 14 54 167 196 133 218 7 174
    232 18 164 200 207 64 99 84 19 124 205 81 244 138 210 221 92 60 6
    143 180 173 242 18 144 106 42 0 186 105 189 72 15 143 189 129 157
    164 134 82 150 205 171 235 133 30 75 194 145 140 80 155 187 18 12 30
    204 114 48 122 200 74 81 16 72 167 36 244 42 86 219 164 80 106 157
    127 128 8 99 195 208 150 161 139 59 121 8 36 34 34 34 101 95 73 213
    168 69 195 165 245 24 40 140 214 54 204 186 194 136 150 235 238 241
    7 88 144 59 83 142 230 236 80 32 27 228 34 204 73 16 168 168 2 9 151
    151 0 82 162 117 125 12 9 65 144 0 209 160 47 144 32 0 7 115 107 34
    5 233 105 6 104 26 46 44 198 133 217 135 16 80 204 29 255 140 137
    211 227 208 215 249 171 136 2 132 34 208 10 48 126 73 42 83 185 75
    231 32 246 162 217 158 164 32 238 149 234 129 140 227 247 208 21 185
    11 3 101 128 39 180 19 32 110 69 40 59 232 67 124 32 242 210 145 26
    148 100 122 13 126 140 141 248 101 200 134 250 147 130 109 0 99 132
    0 34 101 225 44 11 97 17 61 32 115 245 215 9 0 68 122 140 111 12 8
    244 65 192 212 250 43 0 100 136 96 35 99 97 24 136 104 133 88 72 239
    40 240 9 148 203 18 80 200 173 110 204 76 67 203 80 214 49 139 57 80
    2 42 130 106 33 97 232 105 5 218 72 3 36 168 137 138 206 68 84 206
    145 235 129 10 3 223 209 213 156 139 58 81 134 102 52 89 48 51 112
    43 221 176 90 237 8 178 40 30 222 160 176 166 49 254 1 133 97 162
    192 145 249 11 43 99 4 43 199 90 34 7 180 13 159 120 72 167 164 194
    79 66 204 112 194 236 237 235 133 140 211 155 208 147 115 139 19 2
    12 60 226 82 34 55 169 77 79 225 72 239 32 226 10 206 154 52 116 236
    141 123 9 128 243 211 208 149 248 139 10 67 12 119 166 126 160 128
    176 141 65 80 201 131 181 129 155 79 252 75 26 201 213 249 145 30 67
    219 128 155 209 221 127 162 44 158 86 37 7 225 69 164 10 231 56 80
    170 250 106 211 48 149 34 57 212 118 106 201 240 237 10 44 14 229 20
    101 250 80 160 96 48 113 64 73 77 64 72 83 160 228 8 18 21 68 148
    152 156 194 8 9 114 216 16 31 152 5 58 67 8 70 178 72 160 149 100 41
    76 65 152 35 184 38 72 222 55 64 182 3 212 125 24 1 64 201 0 203 251
    101 124 2 160 2 35 88 50 117 101 34 90 112 16 117 96 114 228 223 29
    128 112 54 213 237 0 140 240 229 140 214 227 34 130 108 138 5 19 17
    34 15 161 100 15 248 80 118 104 114 66 215 130 144 96 126 12 118 9
    133 208 197 16 196 227 171 129 36 136 59 129 85 167 157 133 138 15
    175 184 104 170 170 202 213 51 1 50 55 213 104 47 193 177 205 78 188
    38 103 52 73 242 3 33 184 116 61 120 77 79 85 120 81 186 180 24 82
    93 0 57 217 216 70 98 105 230 89 31 115 203 113 61 121 24 86 179 112
    56 58 136 47 201 145 79 206 36 164 43 30 145 34 80 226 189 106 0 0
    107 194 208 209 32 19 59 80 8 39 203 0 34 116 201 110 11 169 80 126
    32 242 226 213 19 132 68 126 4 123 136 128 240 69 208 20 122 131 2
    95 136 33 176</data></Descriptors>
<PatternKeypoints>
  <_>
    <Keypoint>
      168. 221.</Keypoint></_>
  <_>
    <Keypoint>
      249. 466.</Keypoint></_>
  <_>
    <Keypoint>
      234. 106.</Keypoint></_>
  <_>
    <Keypoint>
      105. 243.</Keypoint></_>
  <_>
    <Keypoint>
      264. 396.</Keypoint></_>
  <_>
    <Keypoint>
      420. 242.</Keypoint></_>
  <_>
    <Keypoint>
      231. 385.</Keypoint></_>
  <_>
    <Keypoint>
      420. 251.</Keypoint></_>
  <_>
    <Keypoint>
      159. 253.</Keypoint></_>
  <_>
    <Keypoint>
      300. 253.</Keypoint></_>
  <_>
    <Keypoint>
      257. 99.</Keypoint></_>
  <_>
    <Keypoint>
      92. 233.</Keypoint></_>
  <_>
    <Keypoint>
      141. 263.</Keypoint></_>
  <_>
    <Keypoint>
      387. 263.</Keypoint></_>
  <_>
    <Keypoint>
      422. 264.</Keypoint></_>
  <_>
    <Keypoint>
      247. 221.</Keypoint></_>
  <_>
    <Keypoint>
      221. 120.</Keypoint></_>
  <_>
    <Keypoint>
      227. 221.</Keypoint></_>
  <_>
    <Keypoint>
      199. 221.</Keypoint></_>
  <_>
    <Keypoint>
      291. 268.</Keypoint></_>
  <_>
    <Keypoint>
      249. 31.</Keypoint></_>
  <_>
    <Keypoint>
      303. 268.</Keypoint></_>
  <_>
    <Keypoint>
      294. 253.</Keypoint></_>
  <_>
    <Keypoint>
      105. 252.</Keypoint></_>
  <_>
    <Keypoint>
      349. 246.</Keypoint></_>
  <_>
    <Keypoint>
      113. 221.</Keypoint></_>
  <_>
    <Keypoint>
      404. 233.</Keypoint></_>
  <_>
    <Keypoint>
      80. 221.</Keypoint></_>
  <_>
    <Keypoint>
      181. 275.</Keypoint></_>
  <_>
    <Keypoint>
      187. 275.</Keypoint></_>
  <_>
    <Keypoint>
      422. 221.</Keypoint></_>
  <_>
    <Keypoint>
      392. 221.</Keypoint></_>
  <_>
    <Keypoint>
      369. 221.</Keypoint></_>
  <_>
    <Keypoint>
      359. 221.</Keypoint></_>
  <_>
    <Keypoint>
      320. 221.</Keypoint></_>
  <_>
    <Keypoint>
      274. 221.</Keypoint></_>
  <_>
    <Keypoint>
      233. 221.</Keypoint></_>
  <_>
    <Keypoint>
      185. 221.</Keypoint></_>
  <_>
    <Keypoint>
      123. 221.</Keypoint></_>
  <_>
    <Keypoint>
      108. 221.</Keypoint></_>
  <_>
    <Keypoint>
      284. 126.</Keypoint></_>
  <_>
    <Keypoint>
      219. 275.</Keypoint></_>
  <_>
    <Keypoint>
      267. 275.</Keypoint></_>
  <_>
    <Keypoint>
      263. 129.</Keypoint></_>
  <_>
    <Keypoint>
      387. 275.</Keypoint></_>
  <_>
    <Keypoint>
      392. 275.</Keypoint></_>
  <_>
    <Keypoint>
      422. 275.</Keypoint></_>
  <_>
    <Keypoint>
      285. 167.</Keypoint></_>
  <_>
    <Keypoint>
      221. 167.</Keypoint></_>
  <_>
    <Keypoint>
      247. 401.</Keypoint></_>
  <_>
    <Keypoint>
      235. 136.</Keypoint></_>
  <_>
    <Keypoint>
      285. 170.</Keypoint></_>
  <_>
    <Keypoint>
      221. 170.</Keypoint></_>
  <_>
    <Keypoint>
      249. 85.</Keypoint></_>
  <_>
    <Keypoint>
      260. 221.</Keypoint></_>
  <_>
    <Keypoint>
      193. 275.</Keypoint></_>
  <_>
    <Keypoint>
      332. 253.</Keypoint></_>
  <_>
    <Keypoint>
      332. 263.</Keypoint></_>
  <_>
    <Keypoint>
      212. 221.</Keypoint></_>
  <_>
    <Keypoint>
      359. 275.</Keypoint></_>
  <_>
    <Keypoint>
      243. 411.</Keypoint></_>
  <_>
    <Keypoint>
      92. 254.</Keypoint></_>
  <_>
    <Keypoint>
      404. 262.</Keypoint></_>
  <_>
    <Keypoint>
      371. 261.</Keypoint></_>
  <_>
    <Keypoint>
      125. 261.</Keypoint></_>
  <_>
    <Keypoint>
      404. 253.</Keypoint></_>
  <_>
    <Keypoint>
      332. 241.</Keypoint></_>
  <_>
    <Keypoint>
      247. 393.</Keypoint></_>
  <_>
    <Keypoint>
      288. 275.</Keypoint></_>
  <_>
    <Keypoint>
      241. 275.</Keypoint></_>
  <_>
    <Keypoint>
      233. 275.</Keypoint></_>
  <_>
    <Keypoint>
      247. 59.</Keypoint></_>
  <_>
    <Keypoint>
      80. 275.</Keypoint></_>
  <_>
    <Keypoint>
      332. 232.</Keypoint></_>
  <_>
    <Keypoint>
      168. 267.</Keypoint></_>
  <_>
    <Keypoint>
      91. 275.</Keypoint></_>
  <_>
    <Keypoint>
      113. 275.</Keypoint></_>
  <_>
    <Keypoint>
      156. 268.</Keypoint></_>
  <_>
    <Keypoint>
      153. 275.</Keypoint></_>
  <_>
    <Keypoint>
      303. 221.</Keypoint></_>
  <_>
    <Keypoint>
      404. 240.</Keypoint></_>
  <_>
    <Keypoint>
      172. 275.</Keypoint></_>
  <_>
    <Keypoint>
      230. 412.</Keypoint></_>
  <_>
    <Keypoint>
      321. 275.</Keypoint></_>
  <_>
    <Keypoint>
      315. 275.</Keypoint></_>
  <_>
    <Keypoint>
      422. 231.</Keypoint></_>
  <_>
    <Keypoint>
      273. 275.</Keypoint></_>
  <_>
    <Keypoint>
      291. 221.</Keypoint></_>
  <_>
    <Keypoint>
      108. 231.</Keypoint></_>
  <_>
    <Keypoint>
      257. 275.</Keypoint></_>
  <_>
    <Keypoint>
      250. 275.</Keypoint></_>
  <_>
    <Keypoint>
      227. 275.</Keypoint></_>
  <_>
    <Keypoint>
      243. 387.</Keypoint></_>
  <_>
    <Keypoint>
      254. 385.</Keypoint></_>
  <_>
    <Keypoint>
      464. 215.</Keypoint></_>
  <_>
    <Keypoint>
      202. 275.</Keypoint></_>
  <_>
    <Keypoint>
      338. 232.</Keypoint></_>
  <_>
    <Keypoint>
      264. 159.</Keypoint></_>
  <_>
    <Keypoint>
      306. 275.</Keypoint></_>
  <_>
    <Keypoint>
      156. 221.</Keypoint></_>
  <_>
    <Keypoint>
      264. 97.</Keypoint></_>
  <_>
    <Keypoint>
      210. 275.</Keypoint></_>
  <_>
    <Keypoint>
      338. 241.</Keypoint></_>
  <_>
    <Keypoint>
      226. 136.</Keypoint></_>
  <_>
    <Keypoint>
      253. 383.</Keypoint></_>
  <_>
    <Keypoint>
      455. 206.</Keypoint></_>
  <_>
    <Keypoint>
      458. 209.</Keypoint></_>
  <_>
    <Keypoint>
      446. 197.</Keypoint></_>
  <_>
    <Keypoint>
      340. 233.</Keypoint></_>
  <_>
    <Keypoint>
      2.2680000305175781e+02 1.3680000305175781e+02</Keypoint></_>
  <_>
    <Keypoint>
      144. 264.</Keypoint></_>
  <_>
    <Keypoint>
      2.3160000610351562e+02 3.8520001220703125e+02</Keypoint></_>
  <_>
    <Keypoint>
      2.6760000610351562e+02 2.7480001831054688e+02</Keypoint></_>
  <_>
    <Keypoint>
      3.2160000610351562e+02 2.7480001831054688e+02</Keypoint></_>
  <_>
    <Keypoint>
      4.0440002441406250e+02 2.3280000305175781e+02</Keypoint></_>
  <_>
    <Keypoint>
      2.4120001220703125e+02 2.7480001831054688e+02</Keypoint></_>
  <_>
    <Keypoint>
      3.3240002441406250e+02 2.3280000305175781e+02</Keypoint></_>
  <_>
    <Keypoint>
      2.2680000305175781e+02 2.7480001831054688e+02</Keypoint></_>
  <_>
    <Keypoint>
      9.2400001525878906e+01 2.3280000305175781e+02</Keypoint></_>
  <_>
    <Keypoint>
      4.2120001220703125e+02 2.3040000915527344e+02</Keypoint></_>
  <_>
    <Keypoint>
      2.1960000610351562e+02 2.7480001831054688e+02</Keypoint></_>
  <_>
    <Keypoint>
      2.1000003051757812e+02 2.7480001831054688e+02</Keypoint></_>
  <_>
    <Keypoint>
      2.0280000305175781e+02 2.7480001831054688e+02</Keypoint></_>
  <_>
    <Keypoint>
      1.0800001525878906e+02 2.3040000915527344e+02</Keypoint></_>
  <_>
    <Keypoint>
      1.9320001220703125e+02 2.7480001831054688e+02</Keypoint></_>
  <_>
    <Keypoint>
      3.9240002441406250e+02 2.2080000305175781e+02</Keypoint></_>
  <_>
    <Keypoint>
      3.6840002441406250e+02 2.2080000305175781e+02</Keypoint></_>
  <_>
    <Keypoint>
      3.2040002441406250e+02 2.2080000305175781e+02</Keypoint></_>
  <_>
    <Keypoint>
      1.5240000915527344e+02 2.7480001831054688e+02</Keypoint></_>
  <_>
    <Keypoint>
      1.1400001525878906e+02 2.7480001831054688e+02</Keypoint></_>
  <_>
    <Keypoint>
      90. 2.7480001831054688e+02</Keypoint></_>
  <_>
    <Keypoint>
      2.7360000610351562e+02 2.2080000305175781e+02</Keypoint></_>
  <_>
    <Keypoint>
      8.0400001525878906e+01 2.7480001831054688e+02</Keypoint></_>
  <_>
    <Keypoint>
      2.4720001220703125e+02 3.9360000610351562e+02</Keypoint></_>
  <_>
    <Keypoint>
      2.4720001220703125e+02 6.0000007629394531e+01</Keypoint></_>
  <_>
    <Keypoint>
      2.7960000610351562e+02 2.7480001831054688e+02</Keypoint></_>
  <_>
    <Keypoint>
      2.2680000305175781e+02 2.2080000305175781e+02</Keypoint></_>
  <_>
    <Keypoint>
      186. 2.2080000305175781e+02</Keypoint></_>
  <_>
    <Keypoint>
      2.9160000610351562e+02 2.6760000610351562e+02</Keypoint></_>
  <_>
    <Keypoint>
      2.6520001220703125e+02 3.9600006103515625e+02</Keypoint></_>
  <_>
    <Keypoint>
      168. 2.6760000610351562e+02</Keypoint></_>
  <_>
    <Keypoint>
      1.1400001525878906e+02 2.2080000305175781e+02</Keypoint></_>
  <_>
    <Keypoint>
      1.0800001525878906e+02 2.2080000305175781e+02</Keypoint></_>
  <_>
    <Keypoint>
      4.2240002441406250e+02 264.</Keypoint></_>
  <_>
    <Keypoint>
      3.8640002441406250e+02 264.</Keypoint></_>
  <_>
    <Keypoint>
      1.4040000915527344e+02 264.</Keypoint></_>
  <_>
    <Keypoint>
      8.0400001525878906e+01 2.2080000305175781e+02</Keypoint></_>
  <_>
    <Keypoint>
      2.4840000915527344e+02 84.</Keypoint></_>
  <_>
    <Keypoint>
      2.8440002441406250e+02 1.6920001220703125e+02</Keypoint></_>
  <_>
    <Keypoint>
      2.2080000305175781e+02 1.6920001220703125e+02</Keypoint></_>
  <_>
    <Keypoint>
      3.3240002441406250e+02 2.6280001831054688e+02</Keypoint></_>
  <_>
    <Keypoint>
      4.0440002441406250e+02 2.6160000610351562e+02</Keypoint></_>
  <_>
    <Keypoint>
      3.4080001831054688e+02 2.6160000610351562e+02</Keypoint></_>
  <_>
    <Keypoint>
      372. 2.6040002441406250e+02</Keypoint></_>
  <_>
    <Keypoint>
      1.2600001525878906e+02 2.6040002441406250e+02</Keypoint></_>
  <_>
    <Keypoint>
      3.8640002441406250e+02 2.7480001831054688e+02</Keypoint></_>
  <_>
    <Keypoint>
      3.9240002441406250e+02 2.7480001831054688e+02</Keypoint></_>
  <_>
    <Keypoint>
      342. 2.5680001831054688e+02</Keypoint></_>
  <_>
    <Keypoint>
      4.2240002441406250e+02 2.7480001831054688e+02</Keypoint></_>
  <_>
    <Keypoint>
      2.6520001220703125e+02 1.5840000915527344e+02</Keypoint></_>
  <_>
    <Keypoint>
      3.4080001831054688e+02 2.5440000915527344e+02</Keypoint></_>
  <_>
    <Keypoint>
      2.5680001831054688e+02 9.8400001525878906e+01</Keypoint></_>
  <_>
    <Keypoint>
      9.2400001525878906e+01 2.5440000915527344e+02</Keypoint></_>
  <_>
    <Keypoint>
      2.4720001220703125e+02 4.0080001831054688e+02</Keypoint></_>
  <_>
    <Keypoint>
      4.0440002441406250e+02 2.5320001220703125e+02</Keypoint></_>
  <_>
    <Keypoint>
      2.3040000915527344e+02 4.1280001831054688e+02</Keypoint></_>
  <_>
    <Keypoint>
      2.3400003051757812e+02 1.0560000610351562e+02</Keypoint></_>
  <_>
    <Keypoint>
      4.0440002441406250e+02 2.4000003051757812e+02</Keypoint></_>
  <_>
    <Keypoint>
      3.3240002441406250e+02 2.5320001220703125e+02</Keypoint></_>
  <_>
    <Keypoint>
      300. 2.5320001220703125e+02</Keypoint></_>
  <_>
    <Keypoint>
      2.9520001220703125e+02 2.5320001220703125e+02</Keypoint></_>
  <_>
    <Keypoint>
      2.3520001220703125e+02 1.3680000305175781e+02</Keypoint></_>
  <_>
    <Keypoint>
      2.7240002441406250e+02 2.7480001831054688e+02</Keypoint></_>
  <_>
    <Keypoint>
      3.3240002441406250e+02 2.4120001220703125e+02</Keypoint></_>
  <_>
    <Keypoint>
      1.6440000915527344e+02 2.5320001220703125e+02</Keypoint></_>
  <_>
    <Keypoint>
      1.5960000610351562e+02 2.5320001220703125e+02</Keypoint></_>
  <_>
    <Keypoint>
      2.6280001831054688e+02 1.3080000305175781e+02</Keypoint></_>
  <_>
    <Keypoint>
      1.0440000152587891e+02 2.5200003051757812e+02</Keypoint></_>
  <_>
    <Keypoint>
      4.2000006103515625e+02 2.5080000305175781e+02</Keypoint></_>
  <_>
    <Keypoint>
      4.2000006103515625e+02 2.4240000915527344e+02</Keypoint></_>
  <_>
    <Keypoint>
      288. 2.7480001831054688e+02</Keypoint></_>
  <_>
    <Keypoint>
      2.2080000305175781e+02 1.2000001525878906e+02</Keypoint></_>
  <_>
    <Keypoint>
      1.0440000152587891e+02 2.4360000610351562e+02</Keypoint></_>
  <_>
    <Keypoint>
      2.8440002441406250e+02 1.2600001525878906e+02</Keypoint></_>
  <_>
    <Keypoint>
      3.4920001220703125e+02 2.4600003051757812e+02</Keypoint></_>
  <_>
    <Keypoint>
      2.9160000610351562e+02 2.2080000305175781e+02</Keypoint></_>
  <_>
    <Keypoint>
      2.5440000915527344e+02 3.8520001220703125e+02</Keypoint></_>
  <_>
    <Keypoint>
      258. 2.7480001831054688e+02</Keypoint></_>
  <_>
    <Keypoint>
      2.4240000915527344e+02 4.1040002441406250e+02</Keypoint></_>
  <_>
    <Keypoint>
      2.3280000305175781e+02 2.7480001831054688e+02</Keypoint></_>
  <_>
    <Keypoint>
      3.1440002441406250e+02 2.7480001831054688e+02</Keypoint></_>
  <_>
    <Keypoint>
      168. 2.2080000305175781e+02</Keypoint></_>
  <_>
    <Keypoint>
      1.7160000610351562e+02 2.7480001831054688e+02</Keypoint></_>
  <_>
    <Keypoint>
      3.5880001831054688e+02 2.7480001831054688e+02</Keypoint></_>
  <_>
    <Keypoint>
      2.6040002441406250e+02 2.2080000305175781e+02</Keypoint></_>
  <_>
    <Keypoint>
      306. 2.7480001831054688e+02</Keypoint></_>
  <_>
    <Keypoint>
      156. 2.6760000610351562e+02</Keypoint></_>
  <_>
    <Keypoint>
      3.3960000610351562e+02 2.4000003051757812e+02</Keypoint></_>
  <_>
    <Keypoint>
      4.2240002441406250e+02 2.2080000305175781e+02</Keypoint></_>
  <_>
    <Keypoint>
      2.5056001281738281e+02 3.8160000610351562e+02</Keypoint></_>
  <_>
    <Keypoint>
      2.2608000183105469e+02 2.7360000610351562e+02</Keypoint></_>
  <_>
    <Keypoint>
      2.2608000183105469e+02 2.2176000976562500e+02</Keypoint></_>
  <_>
    <Keypoint>
      2.4768000793457031e+02 4.0032000732421875e+02</Keypoint></_>
  <_>
    <Keypoint>
      2.1888000488281250e+02 2.7360000610351562e+02</Keypoint></_>
  <_>
    <Keypoint>
      1.0656000518798828e+02 2.3040000915527344e+02</Keypoint></_>
  <_>
    <Keypoint>
      4.0464001464843750e+02 2.6064001464843750e+02</Keypoint></_>
  <_>
    <Keypoint>
      1.1376000213623047e+02 2.7360000610351562e+02</Keypoint></_>
  <_>
    <Keypoint>
      8.9280006408691406e+01 2.7360000610351562e+02</Keypoint></_>
  <_>
    <Keypoint>
      8.0639999389648438e+01 2.7360000610351562e+02</Keypoint></_>
  <_>
    <Keypoint>
      1.1376000213623047e+02 2.2032000732421875e+02</Keypoint></_>
  <_>
    <Keypoint>
      1.0656000518798828e+02 2.2032000732421875e+02</Keypoint></_>
  <_>
    <Keypoint>
      4.0464001464843750e+02 2.3328001403808594e+02</Keypoint></_>
  <_>
    <Keypoint>
      2.4048001098632812e+02 2.7360000610351562e+02</Keypoint></_>
  <_>
    <Keypoint>
      3.7152001953125000e+02 2.5920001220703125e+02</Keypoint></_>
  <_>
    <Keypoint>
      3.3264001464843750e+02 2.6208001708984375e+02</Keypoint></_>
  <_>
    <Keypoint>
      3.4127999877929688e+02 2.5920001220703125e+02</Keypoint></_>
  <_>
    <Keypoint>
      2.6640002441406250e+02 2.7360000610351562e+02</Keypoint></_>
  <_>
    <Keypoint>
      3.3264001464843750e+02 2.5344000244140625e+02</Keypoint></_>
  <_>
    <Keypoint>
      2.6496002197265625e+02 3.9600003051757812e+02</Keypoint></_>
  <_>
    <Keypoint>
      2.9952001953125000e+02 2.5200001525878906e+02</Keypoint></_>
  <_>
    <Keypoint>
      2.5632000732421875e+02 9.7920005798339844e+01</Keypoint></_>
  <_>
    <Keypoint>
      1.9152000427246094e+02 2.7360000610351562e+02</Keypoint></_>
  <_>
    <Keypoint>
      3.3264001464843750e+02 2.4048001098632812e+02</Keypoint></_>
  <_>
    <Keypoint>
      2.9376000976562500e+02 2.5200001525878906e+02</Keypoint></_>
  <_>
    <Keypoint>
      1.6416000366210938e+02 2.5200001525878906e+02</Keypoint></_>
  <_>
    <Keypoint>
      2.3328001403808594e+02 1.0512000274658203e+02</Keypoint></_>
  <_>
    <Keypoint>
      2.5344000244140625e+02 3.8448001098632812e+02</Keypoint></_>
  <_>
    <Keypoint>
      1.5984001159667969e+02 2.5200001525878906e+02</Keypoint></_>
  <_>
    <Keypoint>
      4.1904000854492188e+02 2.5056001281738281e+02</Keypoint></_>
  <_>
    <Keypoint>
      3.4992001342773438e+02 2.4480000305175781e+02</Keypoint></_>
  <_>
    <Keypoint>
      3.4127999877929688e+02 2.5632000732421875e+02</Keypoint></_>
  <_>
    <Keypoint>
      1.0368000793457031e+02 2.4336001586914062e+02</Keypoint></_>
  <_>
    <Keypoint>
      4.1904000854492188e+02 2.4192001342773438e+02</Keypoint></_>
  <_>
    <Keypoint>
      2.3184001159667969e+02 3.8448001098632812e+02</Keypoint></_>
  <_>
    <Keypoint>
      9.2160003662109375e+01 2.4048001098632812e+02</Keypoint></_>
  <_>
    <Keypoint>
      9.2160003662109375e+01 2.3328001403808594e+02</Keypoint></_>
  <_>
    <Keypoint>
      2.2032000732421875e+02 1.1952000427246094e+02</Keypoint></_>
  <_>
    <Keypoint>
      3.8592001342773438e+02 2.7360000610351562e+02</Keypoint></_>
  <_>
    <Keypoint>
      3.9312002563476562e+02 2.7360000610351562e+02</Keypoint></_>
  <_>
    <Keypoint>
      2.8655999755859375e+02 2.7360000610351562e+02</Keypoint></_>
  <_>
    <Keypoint>
      1.0368000793457031e+02 2.5056001281738281e+02</Keypoint></_>
  <_>
    <Keypoint>
      1.8576000976562500e+02 2.2032000732421875e+02</Keypoint></_>
  <_>
    <Keypoint>
      2.7936001586914062e+02 2.7360000610351562e+02</Keypoint></_>
  <_>
    <Keypoint>
      2.5344000244140625e+02 3.8736001586914062e+02</Keypoint></_>
  <_>
    <Keypoint>
      2.3472001647949219e+02 1.3536000061035156e+02</Keypoint></_>
  <_>
    <Keypoint>
      2.8368002319335938e+02 1.6848001098632812e+02</Keypoint></_>
  <_>
    <Keypoint>
      2.2176000976562500e+02 1.6848001098632812e+02</Keypoint></_>
  <_>
    <Keypoint>
      4.0464001464843750e+02 2.5344000244140625e+02</Keypoint></_>
  <_>
    <Keypoint>
      2.6208001708984375e+02 1.3104000854492188e+02</Keypoint></_>
  <_>
    <Keypoint>
      2.5632000732421875e+02 2.7360000610351562e+02</Keypoint></_>
  <_>
    <Keypoint>
      8.0639999389648438e+01 2.2032000732421875e+02</Keypoint></_>
  <_>
    <Keypoint>
      1.3968000793457031e+02 2.6352001953125000e+02</Keypoint></_>
  <_>
    <Keypoint>
      4.2048001098632812e+02 2.2032000732421875e+02</Keypoint></_>
  <_>
    <Keypoint>
      2.3040000915527344e+02 4.1184002685546875e+02</Keypoint></_>
  <_>
    <Keypoint>
      2.0880000305175781e+02 2.7360000610351562e+02</Keypoint></_>
  <_>
    <Keypoint>
      1.5696000671386719e+02 2.2032000732421875e+02</Keypoint></_>
  <_>
    <Keypoint>
      2.3328001403808594e+02 2.7360000610351562e+02</Keypoint></_>
  <_>
    <Keypoint>
      3.1392001342773438e+02 2.7360000610351562e+02</Keypoint></_>
  <_>
    <Keypoint>
      1.6704000854492188e+02 2.6783999633789062e+02</Keypoint></_>
  <_>
    <Keypoint>
      2.6064001464843750e+02 1.2672000122070312e+02</Keypoint></_>
  <_>
    <Keypoint>
      3.9168002319335938e+02 2.2032000732421875e+02</Keypoint></_>
  <_>
    <Keypoint>
      3.3984002685546875e+02 2.3472001647949219e+02</Keypoint></_>
  <_>
    <Keypoint>
      2.4048001098632812e+02 3.8592001342773438e+02</Keypoint></_>
  <_>
    <Keypoint>
      1.7136000061035156e+02 2.7360000610351562e+02</Keypoint></_>
  <_>
    <Keypoint>
      9.2160003662109375e+01 2.5344000244140625e+02</Keypoint></_>
  <_>
    <Keypoint>
      2.4768000793457031e+02 3.9312002563476562e+02</Keypoint></_>
  <_>
    <Keypoint>
      2.4624000549316406e+02 2.2032000732421875e+02</Keypoint></_>
  <_>
    <Keypoint>
      3.3984002685546875e+02 2.5344000244140625e+02</Keypoint></_>
  <_>
    <Keypoint>
      3.3264001464843750e+02 2.3184001159667969e+02</Keypoint></_>
  <_>
    <Keypoint>
      2.4912001037597656e+02 2.7360000610351562e+02</Keypoint></_>
  <_>
    <Keypoint>
      4.2192001342773438e+02 2.7360000610351562e+02</Keypoint></_>
  <_>
    <Keypoint>
      3.5856002807617188e+02 2.7360000610351562e+02</Keypoint></_>
  <_>
    <Keypoint>
      4.2048001098632812e+02 2.3040000915527344e+02</Keypoint></_>
  <_>
    <Keypoint>
      3.1968002319335938e+02 2.2032000732421875e+02</Keypoint></_>
  <_>
    <Keypoint>
      2.4883203125000000e+02 2.7302401733398438e+02</Keypoint></_>
  <_>
    <Keypoint>
      2.3155201721191406e+02 4.1299203491210938e+02</Keypoint></_>
  <_>
    <Keypoint>
      3.6633602905273438e+02 2.2118402099609375e+02</Keypoint></_>
  <_>
    <Keypoint>
      2.6611203002929688e+02 3.9571203613281250e+02</Keypoint></_>
  <_>
    <Keypoint>
      2.7993603515625000e+02 2.7302401733398438e+02</Keypoint></_>
  <_>
    <Keypoint>
      1.2096001434326172e+02 2.2118402099609375e+02</Keypoint></_>
  <_>
    <Keypoint>
      2.3155201721191406e+02 3.8361602783203125e+02</Keypoint></_>
  <_>
    <Keypoint>
      3.5942404174804688e+02 2.7302401733398438e+02</Keypoint></_>
  <_>
    <Keypoint>
      2.5228802490234375e+02 3.8707202148437500e+02</Keypoint></_>
  <_>
    <Keypoint>
      2.5056002807617188e+02 3.8188803100585938e+02</Keypoint></_>
  <_>
    <Keypoint>
      2.6611203002929688e+02 2.7302401733398438e+02</Keypoint></_>
  <_>
    <Keypoint>
      2.4019201660156250e+02 2.7302401733398438e+02</Keypoint></_>
  <_>
    <Keypoint>
      2.3328002929687500e+02 2.7302401733398438e+02</Keypoint></_>
  <_>
    <Keypoint>
      2.5574401855468750e+02 9.6768005371093750e+01</Keypoint></_>
  <_>
    <Keypoint>
      2.2464001464843750e+02 2.7302401733398438e+02</Keypoint></_>
  <_>
    <Keypoint>
      2.6092803955078125e+02 2.2118402099609375e+02</Keypoint></_>
  <_>
    <Keypoint>
      2.0563201904296875e+02 2.7302401733398438e+02</Keypoint></_>
  <_>
    <Keypoint>
      1.0540801239013672e+02 2.2809602355957031e+02</Keypoint></_>
  <_>
    <Keypoint>
      2.1945602416992188e+02 2.7302401733398438e+02</Keypoint></_>
  <_>
    <Keypoint>
      2.3328002929687500e+02 2.2118402099609375e+02</Keypoint></_>
  <_>
    <Keypoint>
      1.9180801391601562e+02 2.7302401733398438e+02</Keypoint></_>
  <_>
    <Keypoint>
      2.2464001464843750e+02 2.2118402099609375e+02</Keypoint></_>
  <_>
    <Keypoint>
      2.4537602233886719e+02 2.2118402099609375e+02</Keypoint></_>
  <_>
    <Keypoint>
      2.1945602416992188e+02 1.1750401306152344e+02</Keypoint></_>
  <_>
    <Keypoint>
      1.1404801177978516e+02 2.7302401733398438e+02</Keypoint></_>
  <_>
    <Keypoint>
      8.9856010437011719e+01 2.7302401733398438e+02</Keypoint></_>
  <_>
    <Keypoint>
      8.1216011047363281e+01 2.7302401733398438e+02</Keypoint></_>
  <_>
    <Keypoint>
      3.9225604248046875e+02 2.2118402099609375e+02</Keypoint></_>
  <_>
    <Keypoint>
      4.1990405273437500e+02 2.2118402099609375e+02</Keypoint></_>
  <_>
    <Keypoint>
      9.3312011718750000e+01 2.3328002929687500e+02</Keypoint></_>
  <_>
    <Keypoint>
      4.1990405273437500e+02 2.6438403320312500e+02</Keypoint></_>
  <_>
    <Keypoint>
      3.7152005004882812e+02 2.5920001220703125e+02</Keypoint></_>
  <_>
    <Keypoint>
      3.4041604614257812e+02 2.5920001220703125e+02</Keypoint></_>
  <_>
    <Keypoint>
      2.6265603637695312e+02 1.3132801818847656e+02</Keypoint></_>
  <_>
    <Keypoint>
      2.3328002929687500e+02 1.3478401184082031e+02</Keypoint></_>
  <_>
    <Keypoint>
      3.4041604614257812e+02 2.5574401855468750e+02</Keypoint></_>
  <_>
    <Keypoint>
      8.1216011047363281e+01 2.2118402099609375e+02</Keypoint></_>
  <_>
    <Keypoint>
      4.0435205078125000e+02 2.5401602172851562e+02</Keypoint></_>
  <_>
    <Keypoint>
      2.5574401855468750e+02 2.7302401733398438e+02</Keypoint></_>
  <_>
    <Keypoint>
      9.3312011718750000e+01 2.5401602172851562e+02</Keypoint></_>
  <_>
    <Keypoint>
      2.9894403076171875e+02 2.5056002807617188e+02</Keypoint></_>
  <_>
    <Keypoint>
      4.0435205078125000e+02 2.3328002929687500e+02</Keypoint></_>
  <_>
    <Keypoint>
      1.6416001892089844e+02 2.5056002807617188e+02</Keypoint></_>
  <_>
    <Keypoint>
      3.3868801879882812e+02 2.3673602294921875e+02</Keypoint></_>
  <_>
    <Keypoint>
      4.1990405273437500e+02 2.4883203125000000e+02</Keypoint></_>
  <_>
    <Keypoint>
      1.0540801239013672e+02 2.2118402099609375e+02</Keypoint></_>
  <_>
    <Keypoint>
      3.3350402832031250e+02 2.3155201721191406e+02</Keypoint></_>
  <_>
    <Keypoint>
      1.1404801177978516e+02 2.2118402099609375e+02</Keypoint></_>
  <_>
    <Keypoint>
      1.0368000793457031e+02 2.4364802551269531e+02</Keypoint></_>
  <_>
    <Keypoint>
      4.1817602539062500e+02 2.4192002868652344e+02</Keypoint></_>
  <_>
    <Keypoint>
      3.3350402832031250e+02 2.4019201660156250e+02</Keypoint></_>
  <_>
    <Keypoint>
      4.0435205078125000e+02 2.3846401977539062e+02</Keypoint></_>
  <_>
    <Keypoint>
      9.3312011718750000e+01 2.3846401977539062e+02</Keypoint></_>
  <_>
    <Keypoint>
      3.5942404174804688e+02 2.2118402099609375e+02</Keypoint></_>
  <_>
    <Keypoint>
      2.3328002929687500e+02 1.0368000793457031e+02</Keypoint></_>
  <_>
    <Keypoint>
      2.4883203125000000e+02 4.1472003173828125e+02</Keypoint></_>
  <_>
    <Keypoint>
      2.5228802490234375e+02 4.1472003173828125e+02</Keypoint></_>
  <_>
    <Keypoint>
      4.1990405273437500e+02 2.2982402038574219e+02</Keypoint></_>
  <_>
    <Keypoint>
      4.0435205078125000e+02 2.6092803955078125e+02</Keypoint></_>
  <_>
    <Keypoint>
      3.1968002319335938e+02 2.2118402099609375e+02</Keypoint></_>
  <_>
    <Keypoint>
      2.0217602539062500e+02 2.7302401733398438e+02</Keypoint></_>
  <_>
    <Keypoint>
      3.1276803588867188e+02 2.7302401733398438e+02</Keypoint></_>
  <_>
    <Keypoint>
      1.2614401245117188e+02 2.5920001220703125e+02</Keypoint></_>
  <_>
    <Keypoint>
      4.1886724853515625e+02 2.4883203125000000e+02</Keypoint></_>
  <_>
    <Keypoint>
      2.5090563964843750e+02 4.1472006225585938e+02</Keypoint></_>
  <_>
    <Keypoint>
      1.0368001556396484e+02 2.5090563964843750e+02</Keypoint></_>
  <_>
    <Keypoint>
      2.3224320983886719e+02 4.1264645385742188e+02</Keypoint></_>
  <_>
    <Keypoint>
      2.5505284118652344e+02 4.1057284545898438e+02</Keypoint></_>
  <_>
    <Keypoint>
      3.3384963989257812e+02 2.3846403503417969e+02</Keypoint></_>
  <_>
    <Keypoint>
      9.3312011718750000e+01 2.3846403503417969e+02</Keypoint></_>
  <_>
    <Keypoint>
      3.3799685668945312e+02 2.3639041137695312e+02</Keypoint></_>
  <_>
    <Keypoint>
      2.9859844970703125e+02 2.5090563964843750e+02</Keypoint></_>
  <_>
    <Keypoint>
      2.4675843811035156e+02 3.9605764770507812e+02</Keypoint></_>
  <_>
    <Keypoint>
      2.6542083740234375e+02 1.3478399658203125e+02</Keypoint></_>
  <_>
    <Keypoint>
      3.3384963989257812e+02 2.3224320983886719e+02</Keypoint></_>
  <_>
    <Keypoint>
      3.3384963989257812e+02 2.5297923278808594e+02</Keypoint></_>
  <_>
    <Keypoint>
      4.1886724853515625e+02 2.2809603881835938e+02</Keypoint></_>
  <_>
    <Keypoint>
      4.1886724853515625e+02 2.2187522888183594e+02</Keypoint></_>
  <_>
    <Keypoint>
      3.2140805053710938e+02 2.2187522888183594e+02</Keypoint></_>
  <_>
    <Keypoint>
      2.5090563964843750e+02 3.8568966674804688e+02</Keypoint></_>
  <_>
    <Keypoint>
      2.6127365112304688e+02 2.2187522888183594e+02</Keypoint></_>
  <_>
    <Keypoint>
      2.4468482971191406e+02 2.2187522888183594e+02</Keypoint></_>
  <_>
    <Keypoint>
      2.3431683349609375e+02 2.2187522888183594e+02</Keypoint></_>
  <_>
    <Keypoint>
      4.1886724853515625e+02 2.4261123657226562e+02</Keypoint></_>
  <_>
    <Keypoint>
      1.0368001556396484e+02 2.4261123657226562e+02</Keypoint></_>
  <_>
    <Keypoint>
      2.3224320983886719e+02 3.8361605834960938e+02</Keypoint></_>
  <_>
    <Keypoint>
      2.2394883728027344e+02 2.2187522888183594e+02</Keypoint></_>
  <_>
    <Keypoint>
      3.4007043457031250e+02 2.5920004272460938e+02</Keypoint></_>
  <_>
    <Keypoint>
      1.8662402343750000e+02 2.2187522888183594e+02</Keypoint></_>
  <_>
    <Keypoint>
      1.2026881408691406e+02 2.2187522888183594e+02</Keypoint></_>
  <_>
    <Keypoint>
      4.0435205078125000e+02 2.3846403503417969e+02</Keypoint></_>
  <_>
    <Keypoint>
      2.5297923278808594e+02 2.7371524047851562e+02</Keypoint></_>
  <_>
    <Keypoint>
      2.3224320983886719e+02 1.3478399658203125e+02</Keypoint></_>
  <_>
    <Keypoint>
      2.2187522888183594e+02 2.7371524047851562e+02</Keypoint></_>
  <_>
    <Keypoint>
      2.0528642272949219e+02 2.7164163208007812e+02</Keypoint></_>
  <_>
    <Keypoint>
      2.3639041137695312e+02 2.7164163208007812e+02</Keypoint></_>
  <_>
    <Keypoint>
      1.1612160491943359e+02 2.1980163574218750e+02</Keypoint></_>
  <_>
    <Keypoint>
      2.2809603881835938e+02 1.3685762023925781e+02</Keypoint></_>
  <_>
    <Keypoint>
      1.2648961639404297e+02 2.5920004272460938e+02</Keypoint></_>
  <_>
    <Keypoint>
      2.7164163208007812e+02 2.2187522888183594e+02</Keypoint></_>
  <_>
    <Keypoint>
      2.4675843811035156e+02 8.0870414733886719e+01</Keypoint></_>
  <_>
    <Keypoint>
      2.1358082580566406e+02 2.2187522888183594e+02</Keypoint></_>
  <_>
    <Keypoint>
      9.3312011718750000e+01 2.5505284118652344e+02</Keypoint></_>
  <_>
    <Keypoint>
      1.6174082946777344e+02 2.5090563964843750e+02</Keypoint></_>
  <_>
    <Keypoint>
      2.5505284118652344e+02 4.0642565917968750e+02</Keypoint></_>
  <_>
    <Keypoint>
      2.3224320983886719e+02 1.0160641479492188e+02</Keypoint></_>
  <_>
    <Keypoint>
      3.5873284912109375e+02 2.2187522888183594e+02</Keypoint></_>
  <_>
    <Keypoint>
      2.1980163574218750e+02 1.1612160491943359e+02</Keypoint></_>
  <_>
    <Keypoint>
      2.6749444580078125e+02 2.7371524047851562e+02</Keypoint></_>
  <_>
    <Keypoint>
      1.1404801940917969e+02 2.7371524047851562e+02</Keypoint></_>
  <_>
    <Keypoint>
      4.2094085693359375e+02 2.6542083740234375e+02</Keypoint></_>
  <_>
    <Keypoint>
      8.0870414733886719e+01 2.2187522888183594e+02</Keypoint></_>
  <_>
    <Keypoint>
      3.6702725219726562e+02 2.2187522888183594e+02</Keypoint></_>
  <_>
    <Keypoint>
      1.9077122497558594e+02 2.7371524047851562e+02</Keypoint></_>
  <_>
    <Keypoint>
      3.5873284912109375e+02 2.7371524047851562e+02</Keypoint></_>
  <_>
    <Keypoint>
      4.2052618408203125e+02 2.2892547607421875e+02</Keypoint></_>
  <_>
    <Keypoint>
      2.8615686035156250e+02 2.7371527099609375e+02</Keypoint></_>
  <_>
    <Keypoint>
      2.4634371948242188e+02 7.9626251220703125e+01</Keypoint></_>
  <_>
    <Keypoint>
      2.2394885253906250e+02 2.2394885253906250e+02</Keypoint></_>
  <_>
    <Keypoint>
      2.5380870056152344e+02 2.7371527099609375e+02</Keypoint></_>
  <_>
    <Keypoint>
      9.4556182861328125e+01 2.3639045715332031e+02</Keypoint></_>
  <_>
    <Keypoint>
      2.0653060913085938e+02 2.7371527099609375e+02</Keypoint></_>
  <_>
    <Keypoint>
      4.2052618408203125e+02 2.6873861694335938e+02</Keypoint></_>
  <_>
    <Keypoint>
      2.3141381835937500e+02 9.9532814025878906e+01</Keypoint></_>
  <_>
    <Keypoint>
      2.3390211486816406e+02 3.8320138549804688e+02</Keypoint></_>
  <_>
    <Keypoint>
      3.8568969726562500e+02 2.5878530883789062e+02</Keypoint></_>
  <_>
    <Keypoint>
      2.3639045715332031e+02 2.2394885253906250e+02</Keypoint></_>
  <_>
    <Keypoint>
      2.5132035827636719e+02 4.1306121826171875e+02</Keypoint></_>
  <_>
    <Keypoint>
      2.3390211486816406e+02 4.1306121826171875e+02</Keypoint></_>
  <_>
    <Keypoint>
      2.3887878417968750e+02 4.1057290649414062e+02</Keypoint></_>
  <_>
    <Keypoint>
      2.1897221374511719e+02 1.1446273803710938e+02</Keypoint></_>
  <_>
    <Keypoint>
      3.3841156005859375e+02 2.5629702758789062e+02</Keypoint></_>
  <_>
    <Keypoint>
      8.4602890014648438e+01 2.7122695922851562e+02</Keypoint></_>
  <_>
    <Keypoint>
      1.8911236572265625e+02 2.7122695922851562e+02</Keypoint></_>
  <_>
    <Keypoint>
      4.0559625244140625e+02 2.5629702758789062e+02</Keypoint></_>
  <_>
    <Keypoint>
      9.4556182861328125e+01 2.5629702758789062e+02</Keypoint></_>
  <_>
    <Keypoint>
      1.2690435028076172e+02 2.5878530883789062e+02</Keypoint></_>
  <_>
    <Keypoint>
      2.2146051025390625e+02 2.7122695922851562e+02</Keypoint></_>
  <_>
    <Keypoint>
      2.3141381835937500e+02 1.3188099670410156e+02</Keypoint></_>
  <_>
    <Keypoint>
      4.1803787231445312e+02 2.4883206176757812e+02</Keypoint></_>
  <_>
    <Keypoint>
      1.4183427429199219e+02 2.5878530883789062e+02</Keypoint></_>
  <_>
    <Keypoint>
      2.4883206176757812e+02 3.9564297485351562e+02</Keypoint></_>
  <_>
    <Keypoint>
      2.2892547607421875e+02 1.3685763549804688e+02</Keypoint></_>
  <_>
    <Keypoint>
      4.2052618408203125e+02 2.2146051025390625e+02</Keypoint></_>
  <_>
    <Keypoint>
      1.1446273803710938e+02 2.7371527099609375e+02</Keypoint></_>
  <_>
    <Keypoint>
      1.0202113342285156e+02 2.4634371948242188e+02</Keypoint></_>
  <_>
    <Keypoint>
      3.6080648803710938e+02 2.7122695922851562e+02</Keypoint></_>
  <_>
    <Keypoint>
      2.5132035827636719e+02 3.8568969726562500e+02</Keypoint></_>
  <_>
    <Keypoint>
      3.6329479980468750e+02 2.2146051025390625e+02</Keypoint></_>
  <_>
    <Keypoint>
      3.3343496704101562e+02 2.6127365112304688e+02</Keypoint></_>
  <_>
    <Keypoint>
      2.3639045715332031e+02 2.7122695922851562e+02</Keypoint></_>
  <_>
    <Keypoint>
      2.7122695922851562e+02 2.2146051025390625e+02</Keypoint></_>
  <_>
    <Keypoint>
      2.4385542297363281e+02 2.2146051025390625e+02</Keypoint></_>
  <_>
    <Keypoint>
      2.6873861694335938e+02 2.7122695922851562e+02</Keypoint></_>
  <_>
    <Keypoint>
      1.1695105743408203e+02 2.2146051025390625e+02</Keypoint></_>
  <_>
    <Keypoint>
      4.0559625244140625e+02 2.3639045715332031e+02</Keypoint></_>
  <_>
    <Keypoint>
      1.8662402343750000e+02 2.2146051025390625e+02</Keypoint></_>
  <_>
    <Keypoint>
      3.3592327880859375e+02 2.3887878417968750e+02</Keypoint></_>
  <_>
    <Keypoint>
      8.2114578247070312e+01 2.2146051025390625e+02</Keypoint></_>
  <_>
    <Keypoint>
      1.9707499694824219e+02 2.2096287536621094e+02</Keypoint></_>
  <_>
    <Keypoint>
      1.0152348327636719e+02 2.2394883728027344e+02</Keypoint></_>
  <_>
    <Keypoint>
      2.2992083740234375e+02 9.8537498474121094e+01</Keypoint></_>
  <_>
    <Keypoint>
      2.2394883728027344e+02 1.0152348327636719e+02</Keypoint></_>
  <_>
    <Keypoint>
      3.8519204711914062e+02 2.5679467773437500e+02</Keypoint></_>
  <_>
    <Keypoint>
      9.8537498474121094e+01 2.4485075378417969e+02</Keypoint></_>
  <_>
    <Keypoint>
      1.9110301208496094e+02 2.2394883728027344e+02</Keypoint></_>
  <_>
    <Keypoint>
      2.4783671569824219e+02 3.9414999389648438e+02</Keypoint></_>
  <_>
    <Keypoint>
      2.1797689819335938e+02 1.1346742248535156e+02</Keypoint></_>
  <_>
    <Keypoint>
      2.4783671569824219e+02 3.8220602416992188e+02</Keypoint></_>
  <_>
    <Keypoint>
      3.7026208496093750e+02 2.5679467773437500e+02</Keypoint></_>
  <_>
    <Keypoint>
      2.3290681457519531e+02 3.8220602416992188e+02</Keypoint></_>
  <_>
    <Keypoint>
      3.3741629028320312e+02 2.5679467773437500e+02</Keypoint></_>
  <_>
    <Keypoint>
      9.2565521240234375e+01 2.3589277648925781e+02</Keypoint></_>
  <_>
    <Keypoint>
      2.9561248779296875e+02 2.2096287536621094e+02</Keypoint></_>
  <_>
    <Keypoint>
      2.5082272338867188e+02 2.7172460937500000e+02</Keypoint></_>
  <_>
    <Keypoint>
      2.3589277648925781e+02 2.7172460937500000e+02</Keypoint></_>
  <_>
    <Keypoint>
      2.2096287536621094e+02 2.7172460937500000e+02</Keypoint></_>
  <_>
    <Keypoint>
      3.3443029785156250e+02 2.3290681457519531e+02</Keypoint></_>
  <_>
    <Keypoint>
      2.2992083740234375e+02 1.3735530090332031e+02</Keypoint></_>
  <_>
    <Keypoint>
      2.6575265502929688e+02 2.2096287536621094e+02</Keypoint></_>
  <_>
    <Keypoint>
      1.1346742248535156e+02 2.7172460937500000e+02</Keypoint></_>
  <_>
    <Keypoint>
      3.6130416870117188e+02 2.6873864746093750e+02</Keypoint></_>
  <_>
    <Keypoint>
      2.9561248779296875e+02 2.6873864746093750e+02</Keypoint></_>
  <_>
    <Keypoint>
      2.4485075378417969e+02 2.2096287536621094e+02</Keypoint></_>
  <_>
    <Keypoint>
      2.6873864746093750e+02 2.6873864746093750e+02</Keypoint></_>
  <_>
    <Keypoint>
      2.0304696655273438e+02 2.6873864746093750e+02</Keypoint></_>
  <_>
    <Keypoint>
      1.8811703491210938e+02 2.6873864746093750e+02</Keypoint></_>
  <_>
    <Keypoint>
      3.6130416870117188e+02 2.2096287536621094e+02</Keypoint></_>
  <_>
    <Keypoint>
      2.3887878417968750e+02 2.2096287536621094e+02</Keypoint></_>
  <_>
    <Keypoint>
      1.6124317932128906e+02 2.6873864746093750e+02</Keypoint></_>
  <_>
    <Keypoint>
      2.1797689819335938e+02 2.2096287536621094e+02</Keypoint></_>
  <_>
    <Keypoint>
      4.0310794067382812e+02 2.5679467773437500e+02</Keypoint></_>
  <_>
    <Keypoint>
      1.1943939208984375e+02 2.2096287536621094e+02</Keypoint></_>
  <_>
    <Keypoint>
      1.2541136169433594e+02 2.5679467773437500e+02</Keypoint></_>
  <_>
    <Keypoint>
      1.6124317932128906e+02 2.2096287536621094e+02</Keypoint></_>
  <_>
    <Keypoint>
      2.6157223510742188e+02 2.6515545654296875e+02</Keypoint></_>
  <_>
    <Keypoint>
      1.3616090393066406e+02 2.5798910522460938e+02</Keypoint></_>
  <_>
    <Keypoint>
      3.4756860351562500e+02 2.2932362365722656e+02</Keypoint></_>
  <_>
    <Keypoint>
      2.2215725708007812e+02 2.7232180786132812e+02</Keypoint></_>
  <_>
    <Keypoint>
      1.1466181182861328e+02 2.7232180786132812e+02</Keypoint></_>
  <_>
    <Keypoint>
      3.7265087890625000e+02 2.5798910522460938e+02</Keypoint></_>
  <_>
    <Keypoint>
      3.3681906127929688e+02 2.5798910522460938e+02</Keypoint></_>
  <_>
    <Keypoint>
      1.2541135406494141e+02 2.5798910522460938e+02</Keypoint></_>
  <_>
    <Keypoint>
      3.7981729125976562e+02 2.6873864746093750e+02</Keypoint></_>
  <_>
    <Keypoint>
      2.5440591430664062e+02 2.7232180786132812e+02</Keypoint></_>
  <_>
    <Keypoint>
      1.1824500274658203e+02 2.2574046325683594e+02</Keypoint></_>
  <_>
    <Keypoint>
      2.3649000549316406e+02 3.8340042114257812e+02</Keypoint></_>
  <_>
    <Keypoint>
      3.2248632812500000e+02 2.2215725708007812e+02</Keypoint></_>
  <_>
    <Keypoint>
      2.9740405273437500e+02 2.2215725708007812e+02</Keypoint></_>
  <_>
    <Keypoint>
      2.6515545654296875e+02 2.2215725708007812e+02</Keypoint></_>
  <_>
    <Keypoint>
      2.4007318115234375e+02 2.2215725708007812e+02</Keypoint></_>
  <_>
    <Keypoint>
      2.1857409667968750e+02 2.2215725708007812e+02</Keypoint></_>
  <_>
    <Keypoint>
      1.8632543945312500e+02 2.2215725708007812e+02</Keypoint></_>
  <_>
    <Keypoint>
      1.6124316406250000e+02 2.2215725708007812e+02</Keypoint></_>
  <_>
    <Keypoint>
      2.7232180786132812e+02 2.6873864746093750e+02</Keypoint></_>
  <_>
    <Keypoint>
      2.3649000549316406e+02 2.7232180786132812e+02</Keypoint></_>
  <_>
    <Keypoint>
      3.8698361206054688e+02 2.5798910522460938e+02</Keypoint></_>
  <_>
    <Keypoint>
      1.4332725524902344e+02 2.5798910522460938e+02</Keypoint></_>
  <_>
    <Keypoint>
      2.6515545654296875e+02 3.8340042114257812e+02</Keypoint></_>
  <_>
    <Keypoint>
      2.5082270812988281e+02 3.8698361206054688e+02</Keypoint></_>
  <_>
    <Keypoint>
      3.4040228271484375e+02 2.2215725708007812e+02</Keypoint></_>
  <_>
    <Keypoint>
      1.8632543945312500e+02 2.7232180786132812e+02</Keypoint></_>
  <_>
    <Keypoint>
      3.3681906127929688e+02 2.3649000549316406e+02</Keypoint></_>
  <_>
    <Keypoint>
      2.1857409667968750e+02 1.1107862854003906e+02</Keypoint></_>
  <_>
    <Keypoint>
      3.5473501586914062e+02 2.7232180786132812e+02</Keypoint></_>
  <_>
    <Keypoint>
      2.0424134826660156e+02 2.7232180786132812e+02</Keypoint></_></PatternKeypoints>
<BoundingBox>
  <_>
    <Corner>
      0. 0.</Corner></_>
  <_>
    <Corner>
      500. 0.</Corner></_>
  <_>
    <Corner>
      500. 500.</Corner></_>
  <_>
    <Corner>
      0. 500.</Corner></_>
  <_>
    <Corner>
      250. 250.</Corner></_></BoundingBox>
</opencv_storage>
